Workbook

Sheet Từ Vựng Tiếng Anh Lớp 10
A1: Topic | B1: Term | C1: PartOfSpeech | D1: Phonetic | E1: Definition | F1: CEFR | G1: Example | H1: Synonyms | I1: Antonyms | J1: Collocations | K1: Note
A2: Unit 1: Family Life | B2: breadwinner | C2: noun | D2: /ˈbredˌwɪn.ər/ | E2: Trụ cột gia đình (người kiếm tiền chính nuôi sống gia đình) | F2: B2 | G2: In many modern families, both the husband and wife are equal breadwinners. | H2: primary earner, sole provider | I2: dependent, dependent child | J2: sole breadwinner, main breadwinner, act as the breadwinner | K2: Ghép từ 'bread' (bánh mì/kế sinh nhai) + 'winner' (người kiếm về).
A3: Unit 1: Family Life | B3: homemaker | C3: noun | D3: /ˈhəʊmˌmeɪ.kər/ | E3: Người nội trợ (người quán xuyến việc nhà và chăm sóc con cái) | F3: B1 | G3: Being a full-time homemaker requires patience, organization, and dedication. | H3: housewife, househusband, caregiver | I3: breadwinner, office worker | J3: full-time homemaker, skilled homemaker, work as a homemaker | K3: Từ trung tính giới, thay thế cho từ 'housewife' truyền thống.
A4: Unit 1: Family Life | B4: heavy lifting | C4: noun phrase | D4: /ˌhev.i ˈlɪf.tɪŋ/ | E4: Công việc nặng nhọc, mang vác đồ nặng trong gia đình | F4: B1 | G4: My brother often helps my parents with the heavy lifting around the house. | H4: strenuous work, hard physical labor | I4: light duty, easy chore | J4: do the heavy lifting, assist with heavy lifting | K4: Nghĩa bóng: giải quyết phần công việc gian nan nhất trong một dự án.
A5: Unit 1: Family Life | B5: financial burden | C5: noun phrase | D5: /faɪˈnæn.ʃəl ˈbɜː.dən/ | E5: Gánh nặng tài chính, áp lực tiền bạc nuôi sống gia đình | F5: B2 | G5: Sharing living expenses helps ease the financial burden on parents. | H5: economic pressure, monetary strain | I5: financial freedom, financial ease | J5: ease the financial burden, shoulder the financial burden, heavy financial burden | K5: Động từ đi kèm: ease / relieve (giảm bớt), shoulder / bear (gánh vác).
A6: Unit 1: Family Life | B6: split chores | C6: verb phrase | D6: /splɪt tʃɔːz/ | E6: Phân chia công việc nhà đều đặn giữa các thành viên | F6: B1 | G6: Happy families often split household chores equally between all members. | H6: divide household chores, share domestic duties | I6: leave all chores to one person | J6: split chores equally, agree to split chores, chore allocation | K6: 'Split' có quá khứ và phân từ hai đều là 'split'.
A7: Unit 1: Family Life | B7: gratitude | C7: noun | D7: /ˈɡræt.ɪ.tʃuːd/ | E7: Lòng biết ơn, sự tri ân sâu sắc đối với cha mẹ và người thân | F7: B2 | G7: Children should express their heartfelt gratitude to parents for their unconditional care. | H7: thankfulness, appreciation, gratefulness | I7: ingratitude, ungratefulness | J7: express gratitude, show gratitude, deep gratitude, feeling of gratitude | K7: Tính từ là 'grateful' (grateful to someone for something).
A8: Unit 2: Humans & Environment | B8: carbon footprint | C8: noun phrase | D8: /ˌkɑː.bən ˈfʊt.prɪnt/ | E8: Dấu chân carbon (tổng lượng khí nhà kính sinh ra từ hoạt động con người) | F8: B2 | G8: Commuting by public transport is an effective way to minimize your carbon footprint. | H8: greenhouse gas emission, carbon output | I8: zero emission | J8: reduce carbon footprint, calculate carbon footprint, zero carbon footprint | K8: Thuật ngữ sinh thái trọng tâm trong kỳ thi tốt nghiệp và kiểm tra 10.
A9: Unit 2: Humans & Environment | B9: eco-friendly | C9: adjective | D9: /ˌiː.kəʊˈfrend.li/ | E9: Thân thiện với môi trường, không gây tổn hại hệ sinh thái | F9: B1 | G9: More consumers are turning to eco-friendly products to reduce plastic pollution. | H9: environmentally friendly, green, sustainable | I9: polluting, harmful to the environment | J9: eco-friendly lifestyle, eco-friendly packaging, eco-friendly materials | K9: Tính từ ghép có gạch nối, thường đứng trước danh từ.
A10: Unit 2: Humans & Environment | B10: biodegradable | C10: adjective | D10: /ˌbaɪ.əʊ.dɪˈɡreɪ.də.bəl/ | E10: Có thể tự phân hủy sinh học một cách tự nhiên | F10: B2 | G10: Supermarkets should replace nylon bags with biodegradable paper containers. | H10: decomposable, compostable | I10: non-biodegradable, indestructible | J10: biodegradable waste, biodegradable plastic, 100% biodegradable | K10: Tiền tố bio- (sinh học) + degrade (phân hủy) + -able (có thể).
A11: Unit 2: Humans & Environment | B11: greenhouse effect | C11: noun phrase | D11: /ˈɡriːn.haʊs ɪˌfekt/ | E11: Hiệu ứng nhà kính (hiện tượng làm Trái Đất ấm dần lên) | F11: B1 | G11: Excessive burning of fossil fuels intensifies the greenhouse effect globally. | H11: global warming phenomenon, thermal entrapment | I11: N/A | J11: intensify the greenhouse effect, greenhouse effect gases, cause the greenhouse effect | K11: Phân biệt 'greenhouse effect' (hiệu ứng) và 'greenhouse gases' (khí nhà kính).
A12: Unit 2: Humans & Environment | B12: energy-efficient | C12: adjective | D12: /ˌen.ə.dʒi.ɪˈfɪʃ.ənt/ | E12: Tiết kiệm năng lượng, hiệu suất năng lượng cao | F12: B2 | G12: Installing energy-efficient LED bulbs cuts down electricity bills significantly. | H12: power-saving, energy-saving, low-consumption | I12: energy-wasting, inefficient | J12: energy-efficient appliances, energy-efficient building, energy-efficient technology | K12: Danh từ tương ứng: 'energy efficiency' (hiệu quả sử dụng năng lượng).
... A61: Unit 10: Ecotourism | B61: environmental impact | C61: noun phrase | D61: /ɪnˌvaɪ.rənˈmen.təl ˈɪm.pækt/ | E61: Tác động môi trường (ảnh hưởng của các hoạt động của con người lên thiên nhiên) | F61: B2 | G61: Before building new resorts, developers must conduct a comprehensive environmental impact assessment. | H61: ecological footprint, environmental effect | I61: N/A | J61: minimize environmental impact, negative environmental impact, assess environmental impact | K61: Cụm từ EIA: Environmental Impact Assessment (Đánh giá tác động môi trường).

Sheet Tổng Quan & Thống Kê
A1: TỔNG HỢP VÀ PHÂN TÍCH TỪ VỰNG TIẾNG ANH LỚP 10
A2: Hệ thống từ vựng học thuật chuẩn hóa theo 10 Unit chương trình GDPT 2018 (Global Success, Friends Global, Bright, i-Learn Smart World)
B4: TỔNG SỐ TỪ VỰNG | D4: SỐ CHỦ ĐỀ (UNITS) | F4: TRÌNH ĐỘ B1 (INTERMEDIATE) | H4: TRÌNH ĐỘ B2 (UPPER-INTER)
B5: =COUNTA('Từ Vựng Tiếng Anh Lớp 10'!B2:B61) | D5: 10 | F5: =COUNTIF('Từ Vựng Tiếng Anh Lớp 10'!F2:F61, "B1") | H5: =COUNTIF('Từ Vựng Tiếng Anh Lớp 10'!F2:F61, "B2")
A8: BẢNG 1: THỐNG KÊ TỪ VỰNG THEO TỪNG CHỦ ĐỀ LỚP 10 | F8: BẢNG 2: PHÂN BỐ THEO TRÌNH ĐỘ CEFR
A9: Mã & Tên Chủ Đề | B9: Số Từ Vựng | C9: Tỷ Lệ (%) | D9: Cấp Độ Mục Tiêu | F9: Cấp Độ CEFR | G9: Số Từ Vựng | H9: Tỷ Lệ (%)
A10: Unit 1: Family Life | B10: =COUNTIF('Từ Vựng Tiếng Anh Lớp 10'!$A$2:$A$61, A10) | C10: =B10/$B$20 | D10: B1 - B2 | F10: A2 | G10: =COUNTIF('Từ Vựng Tiếng Anh Lớp 10'!$F$2:$F$61, "A2") | H10: =G10/$G$13
A11: Unit 2: Humans & Environment | B11: =COUNTIF('Từ Vựng Tiếng Anh Lớp 10'!$A$2:$A$61, A11) | C11: =B11/$B$20 | D11: B1 - B2 | F11: B1 | G11: =COUNTIF('Từ Vựng Tiếng Anh Lớp 10'!$F$2:$F$61, "B1") | H11: =G11/$G$13
A12: Unit 3: Music | B12: =COUNTIF('Từ Vựng Tiếng Anh Lớp 10'!$A$2:$A$61, A12) | C12: =B12/$B$20 | D12: A2 - B2 | F12: B2 | G12: =COUNTIF('Từ Vựng Tiếng Anh Lớp 10'!$F$2:$F$61, "B2") | H12: =G12/$G$13
A13: Unit 4: For a Better Community | B13: =COUNTIF('Từ Vựng Tiếng Anh Lớp 10'!$A$2:$A$61, A13) | C13: =B13/$B$20 | D13: B1 - B2 | F13: Tổng cộng | G13: =SUM(G10:G12) | H13: =SUM(H10:H12)
A14: Unit 5: Inventions | B14: =COUNTIF('Từ Vựng Tiếng Anh Lớp 10'!$A$2:$A$61, A14) | C14: =B14/$B$20 | D14: B1 - B2
A15: Unit 6: Gender Equality | B15: =COUNTIF('Từ Vựng Tiếng Anh Lớp 10'!$A$2:$A$61, A15) | C15: =B15/$B$20 | D15: B2
A16: Unit 7: VN & International Orgs | B16: =COUNTIF('Từ Vựng Tiếng Anh Lớp 10'!$A$2:$A$61, A16) | C16: =B16/$B$20 | D16: B1 - B2
A17: Unit 8: New Ways to Learn | B17: =COUNTIF('Từ Vựng Tiếng Anh Lớp 10'!$A$2:$A$61, A17) | C17: =B17/$B$20 | D17: B1 - B2
A18: Unit 9: Protecting Environment | B18: =COUNTIF('Từ Vựng Tiếng Anh Lớp 10'!$A$2:$A$61, A18) | C18: =B18/$B$20 | D18: B1 - B2
A19: Unit 10: Ecotourism | B19: =COUNTIF('Từ Vựng Tiếng Anh Lớp 10'!$A$2:$A$61, A19) | C19: =B19/$B$20 | D19: A2 - B2
A20: Tổng cộng | B20: =SUM(B10:B19) | C20: =SUM(C10:C19) | D20: Toàn bộ 10 Units
A40: CHIẾN LƯỢC HỌC TỪ VỰNG TIẾNG ANH LỚP 10 ĐẠT ĐIỂM 9+ VÀ CHUẨN BỊ THI TỐT NGHIỆP / IELTS
A41: 1. Bước nhảy vọt từ THCS lên THPT (Nâng tầm vốn từ từ B1 lên B2):
A42: Lớp 10 đòi hỏi học sinh tiếp cận nhiều từ vựng học thuật (academic vocabulary) liên quan đến bình đẳng giới, ngoại giao quốc tế, công nghệ sinh học và môi trường. Hãy chú trọng hiểu sâu nghĩa ngữ cảnh thay vì dịch thô từng từ.
A43: 2. Học Collocations và Cụm động từ cố định (Collocations Mastery):
A44: Điểm số các bài thi trắc nghiệm THPT và Viết luận phụ thuộc rất lớn vào việc dùng đúng cụm từ cố định (ví dụ: 'break gender stereotypes', 'ease financial burden', 'integrate into global economy', 'endangered species').
A45: 3. Khai thác họ từ và quy tắc cấu tạo từ (Word Families & Affixes):
A46: Mỗi khi học một từ, hãy mở rộng sang danh từ, tính từ, trạng từ và tiền tố/hậu tố liên quan (Ví dụ: sustain -> sustainable -> sustainability; innovate -> innovative -> innovation). Dạng bài Word Formation chiếm tỷ lệ điểm quan trọng.
A47: 4. Luyện tập theo ngữ cảnh đọc hiểu (Reading in Context):
A48: Đọc các bài báo tiếng Anh (BBC Learning English, National Geographic, UN News) liên quan trực tiếp đến 10 chủ đề trên để thấy cách người bản xứ sử dụng từ vựng trong văn cảnh thực tế.
A49: 5. Sử dụng Flashcard tương tác và theo dõi tiến độ:
A50: Thường xuyên làm bài tập tại Tab 'Flashcard & Luyện Tập', cập nhật trạng thái 'Cần ôn lại' cho các từ khó hoặc dễ nhầm lẫn để ôn tập định kỳ trước các đợt thi học kỳ.

Sheet Flashcard & Luyện Tập
A1: BẢNG LUYỆN TẬP & ĐÁNH GIÁ MỨC ĐỘ GHI NHỚ TỪ VỰNG TIẾNG ANH LỚP 10
A2: Hướng dẫn: Tự điền từ vào chỗ trống trong câu, sau đó đánh giá mức độ ghi nhớ ở cột 'Trạng Thái Ôn Tập' để lên kế hoạch ôn luyện định kỳ.
A4: STT | B4: Chủ Đề (Topic) | C4: Từ Cần Nhớ (Target Term) | D4: Loại Từ & Phiên Âm | E4: Định Nghĩa Tiếng Việt | F4: Câu Hỏi Luyện Tập (Điền từ vào chỗ trống) | G4: Trạng Thái Ôn Tập | H4: Ghi Chú Ôn Tập Cá Nhân
A5: 1 | B5: Unit 1: Family Life | C5: breadwinner | D5: noun | /ˈbredˌwɪn.ər/ | E5: Trụ cột gia đình | F5: In many modern households, both parents share the financial responsibilities instead of relying on a single _____. | G5: Đã thuộc | H5: Nghĩa đen: kiếm bánh mì -> người kiếm tiền chính
A6: 2 | B6: Unit 1: Family Life | C6: heavy lifting | D6: noun phrase | /ˌhev.i ˈlɪf.tɪŋ/ | E6: Việc nặng nhọc / mang vác | F6: My older brother usually helps my father with the _____ around the house, such as carrying heavy furniture. | G6: Đã thuộc | H6: Học cụm do the heavy lifting
A7: 3 | B7: Unit 1: Family Life | C7: gratitude | D7: noun | /ˈɡræt.ɪ.tʃuːd/ | E7: Lòng biết ơn, tri ân | F7: On Teacher's Day, students express their profound _____ to their mentors for their endless dedication. | G7: Đang học | H7: Tính từ là grateful to sb for sth
A8: 4 | B8: Unit 2: Humans & Environment | C8: carbon footprint | D8: noun phrase | /ˌkɑː.bən ˈfʊt.prɪnt/ | E8: Dấu chân carbon | F8: Choosing to ride a bicycle or take the bus to school significantly reduces your personal _____. | G8: Đã thuộc | H8: Cụm reduce / minimize carbon footprint
A9: 5 | B9: Unit 2: Humans & Environment | C9: biodegradable | D9: adj | /ˌbaɪ.əʊ.dɪˈɡreɪ.də.bəl/ | E9: Phân hủy sinh học | F9: The government encourages restaurants to use _____ packaging made from sugarcane instead of single-use plastic. | G9: Đang học | H9: Trọng âm 4: bio-de-GRA-da-ble
A10: 6 | B10: Unit 2: Humans & Environment | C10: sustainable | D10: adj | /səˈsteɪ.nə.bəl/ | E10: Bền vững, bảo vệ MT | F10: Solar and wind power provide _____ energy alternatives to fossil fuels without depleting resources. | G10: Đã thuộc | H10: Danh từ: sustainability
A11: 7 | B11: Unit 3: Music | C11: compose | D11: verb | /kəmˈpəʊz/ | E11: Sáng tác bản nhạc | F11: Do you know who _____ the famous national anthem 'Tien Quan Ca' of Vietnam? | G11: Đã thuộc | H11: Phân biệt composer (nhạc sĩ) và singer
A12: 8 | B12: Unit 3: Music | C12: audition | D12: noun/verb | /ɔːˈdɪʃ.ən/ | E12: Buổi thử giọng / Thử vai | F12: Over five hundred aspiring young singers registered to _____ for the national voice talent show. | G12: Đang học | H12: Cụm audition for a competition/role
A13: 9 | B13: Unit 3: Music | C13: phenomenon | D13: noun | /fəˈnɒm.ɪ.nən/ | E13: Hiện tượng đặc biệt | F13: The teenage pop sensation became an international musical _____ after her viral debut music video. | G13: Cần ôn lại | H13: Số nhiều là phenomena (đặc biệt)
A14: 10 | B14: Unit 4: For a Better Community | C14: underprivileged | D14: adj | /ˌʌn.dəˈprɪv.əl.ɪdʒd/ | E14: Thiệt thòi, hoàn cảnh khó khăn | F14: The youth volunteer club organized free weekend tutoring classes for _____ children in rural areas. | G14: Đang học | H14: Đồng nghĩa với disadvantaged, needy
A15: 11 | B15: Unit 4: For a Better Community | C15: donate | D15: verb | /dəʊˈneɪt/ | E15: Quyên góp, ủng hộ | F15: Local citizens were encouraged to _____ warm clothes, textbooks, and food to victims of the typhoon. | G15: Đã thuộc | H15: Danh từ donation, người tặng: donor
A16: 12 | B16: Unit 4: For a Better Community | C16: non-profit organization | D16: noun phrase | /ˌnɒnˈprɒf.ɪt ˌɔː.ɡən.aɪˈzeɪ.ʃən/ | E16: Tổ chức phi lợi nhuận | F16: The World Wide Fund for Nature (WWF) is an international _____ dedicated to wildlife protection. | G16: Đã thuộc | H16: Viết tắt là NPO hoặc NGO
... A29: 25 | B29: Unit 10: Ecotourism | C29: ecotourism | D29: noun | /ˈiː.kəʊˌtʊə.rɪ.zəm/ | E29: Du lịch sinh thái | F29: Developing sustainable _____ in national parks creates jobs for locals while protecting pristine forests. | G29: Đã thuộc | H29: Ecology + tourism
