Workbook

Sheet Từ Vựng IELTS 6.0 - 7.0
A1: Topic | B1: Term | C1: PartOfSpeech | D1: Phonetic | E1: Definition | F1: CEFR | G1: Example | H1: Synonyms | I1: Antonyms | J1: Collocations | K1: Note
A2: Education & Academic | B2: pedagogy | C2: noun | D2: /ˈped.ə.ɡɒdʒ.i/ | E2: Phương pháp sư phạm, nghệ thuật và khoa học giảng dạy | F2: C1 | G2: Modern pedagogy emphasizes student-centered learning and interactive problem-solving over rote memorization. | H2: teaching methodology, instructional strategy, educational theory | I2: N/A | J2: innovative pedagogy, pedagogical approach, modern pedagogy | K2: Tính từ: pedagogical /ˌped.əˈɡɒdʒ.ɪ.kəl/. Thường dùng trong Writing Task 2 về giáo dục.
A3: Education & Academic | B3: curriculum | C3: noun | D3: /kəˈrɪk.jə.ləm/ | E3: Chương trình giảng dạy chính khóa của một cơ sở giáo dục | F3: B2 | G3: Educational authorities ought to integrate financial literacy and digital skills into the national school curriculum. | H3: syllabus, academic program, course of study | I3: extracurricular activity | J3: core curriculum, school curriculum, design a curriculum, reform the curriculum | K3: Số nhiều: curricula /kəˈrɪk.jə.lə/ hoặc curriculums. Phân biệt với syllabus (đề cương môn học).
A4: Education & Academic | B4: comprehensive | C4: adjective | D4: /ˌkɒm.prɪˈhen.sɪv/ | E4: Toàn diện, bao quát và đầy đủ mọi khía cạnh | F4: B2 | G4: The university provides a comprehensive range of academic disciplines and specialized vocational training. | H4: all-inclusive, thorough, exhaustive, extensive | I4: limited, incomplete, superficial, partial | J4: comprehensive study, comprehensive review, comprehensive education | K4: Tránh nhầm với 'comprehensible' (dễ hiểu). Comprehensive = toàn diện.
A5: Education & Academic | B5: autonomous | C5: adjective | D5: /ɔːˈtɒn.ə.məs/ | E5: Tự chủ, độc lập tự quản lý việc học tập và nghiên cứu | F5: C1 | G5: Tertiary education aims to produce autonomous learners capable of critical inquiry and independent thought. | H5: self-directed, independent, self-governing | I5: dependent, subordinate, reliant | J5: autonomous learner, autonomous learning, foster learner autonomy | K5: Danh từ: learner autonomy (tính tự chủ trong học tập). Cụm ăn điểm rất cao trong Task 2.
A6: Education & Academic | B6: cognitive | C6: adjective | D6: /ˈkɒɡ.nə.tɪv/ | E6: Thuộc về nhận thức, tư duy và khả năng xử lý thông tin | F6: C1 | G6: Early childhood reading substantially accelerates cognitive development and linguistic proficiency. | H6: intellectual, mental, perceptual, rational | I6: physical, emotional | J6: cognitive development, cognitive ability, cognitive impairment, cognitive skills | K6: Danh từ: cognition /kɒɡˈnɪʃ.ən/ (quá trình nhận thức).
A7: Education & Academic | B7: tertiary education | C7: noun phrase | D7: /ˈtɜː.ʃər.i edʒ.uˈkeɪ.ʃən/ | E7: Giáo dục bậc ba (bậc đại học, cao đẳng và sau đại học) | F7: B2 | G7: Government tuition subsidies allow low-income students to access tertiary education without heavy debts. | H7: higher education, post-secondary education, university level | I7: primary education, secondary education | J7: pursue tertiary education, access to tertiary education, tertiary education institutions | K7: Thuật ngữ học thuật chuẩn mực thay thế cho 'university education' trong IELTS Writing.
A8: Education & Academic | B8: illiteracy | C8: noun | D8: /ɪˈlɪt.ər.ə.si/ | E8: Nạn mù chữ, tình trạng thiếu khả năng đọc viết cơ bản | F8: B2 | G8: Targeted educational initiatives in impoverished rural areas have contributed to eradicating adult illiteracy. | H8: inability to read, analphabetism | I8: literacy, erudition | J8: eradicate illiteracy, illiteracy rate, combat illiteracy | K8: Tính từ: illiterate /ɪˈlɪt.ər.ət/ (mù chữ). Mở rộng: digital illiteracy (mù công nghệ).
A9: Education & Academic | B9: rote learning | C9: noun phrase | D9: /ˈrəʊt ˌlɜː.nɪŋ/ | E9: Học vẹt, học thuộc lòng máy móc không qua thấu hiểu bản chất | F9: C1 | G9: Educational reformers argue that heavy reliance on rote learning suppresses analytical inquiry and creativity. | H9: memorization by repetition, mechanical learning | I9: meaningful learning, experiential learning, critical inquiry | J9: rely on rote learning, rote learning methods, discourage rote learning | K9: Thành ngữ: learn something by rote (học vẹt cái gì).
A10: Education & Academic | B10: holistic | C10: adjective | D10: /həʊˈlɪs.tɪk/ | E10: Toàn diện, tổng thể (xem xét mọi mặt gắn kết thay vì từng phần riêng lẻ) | F10: C1 | G10: Schools should adopt a holistic approach to child assessment rather than relying solely on standardized exam scores. | H10: comprehensive, integrated, all-encompassing, well-rounded | I10: atomistic, fragmented, piecemeal | J10: holistic approach, holistic education, holistic view, holistic assessment | K10: Cụm từ rất hay dùng trong phần đề xuất giải pháp bài Writing Task 2: 'adopt a holistic approach'.
A11: Environment & Sustainability | B11: biodiversity | C11: noun | D11: /ˌbaɪ.əʊ.daɪˈvɜː.sə.ti/ | E11: Đa dạng sinh học (sự phong phú của các loài động thực vật và hệ sinh thái) | F11: B2 | G11: Uncontrolled deforestation and habitat destruction pose an existential threat to global biodiversity. | H11: biological diversity, ecological variety | I11: monoculture, ecological uniformity | J11: loss of biodiversity, preserve biodiversity, rich biodiversity, biodiversity hotspot | K11: Trọng âm 4: bi-o-di-VER-si-ty. Thuật ngữ cốt lõi trong Writing Task 2 về môi trường.
A12: Environment & Sustainability | B12: degradation | C12: noun | D12: /ˌdeɡ.rəˈdeɪ.ʃən/ | E12: Sự suy thoái, xuống cấp nghiêm trọng về chất lượng môi trường/đất đai | F12: C1 | G12: Unregulated industrial discharge accelerates environmental degradation and contaminates local river basins. | H12: deterioration, degeneration, decline, decay | I12: restoration, regeneration, enhancement | J12: environmental degradation, land degradation, soil degradation, reverse degradation | K12: Động từ: degrade (làm suy thoái). Tính từ: degraded.
... A109: Psychology & Behavior | B109: introverted | C109: adjective | D109: /ˈɪn.trə.vɜː.tɪd/ | E109: Hướng nội (có xu hướng suy ngẫm nội tâm và nạp năng lượng khi ở một mình) | F109: B2 | G109: Introverted students may prefer solitary research and written communication over noisy group presentations. | H109: quiet, reserved, introspective, shy | I109: extroverted, outgoing, sociable, gregarious | J109: introverted personality, introverted tendencies, naturally introverted | K109: Danh từ: introvert /ˈɪn.trə.vɜːt/. Trái nghĩa: extroverted / extrovert.

Sheet Tổng Quan & Thống Kê
A1: TỔNG HỢP VÀ PHÂN TÍCH TỪ VỰNG HỌC THUẬT IELTS BAND 6.0 - 7.0+
A2: Hệ thống 108+ từ vựng học thuật trọng tâm phân bổ qua 12 chủ đề cốt lõi của kỳ thi IELTS (Academic Writing Task 1/2, Speaking Parts 1-3 & Reading/Listening)
B4: TỔNG SỐ TỪ VỰNG | D4: SỐ CHỦ ĐỀ CỐT LÕI | F4: TRÌNH ĐỘ B2 (IELTS 5.5-6.5) | H4: TRÌNH ĐỘ C1 (IELTS 7.0-8.0)
B5: =COUNTA('Từ Vựng IELTS 6.0 - 7.0'!B2:B109) | D5: 12 | F5: =COUNTIF('Từ Vựng IELTS 6.0 - 7.0'!F2:F109, "B2") | H5: =COUNTIF('Từ Vựng IELTS 6.0 - 7.0'!F2:F109, "C1")
A8: BẢNG 1: PHÂN BỐ TỪ VỰNG THEO 12 CHỦ ĐỀ IELTS | F8: BẢNG 2: PHÂN BỐ THEO TRÌNH ĐỘ CEFR
A9: Mã & Tên Chủ Đề | B9: Số Từ Vựng | C9: Tỷ Lệ (%) | D9: Mục Tiêu IELTS | F9: Cấp Độ CEFR | G9: Số Từ Vựng | H9: Tỷ Lệ (%)
A10: Education & Academic | B10: =COUNTIF('Từ Vựng IELTS 6.0 - 7.0'!$A$2:$A$109, A10) | C10: =B10/$B$22 | D10: Band 6.5 - 7.5 | F10: B1 | G10: =COUNTIF('Từ Vựng IELTS 6.0 - 7.0'!$F$2:$F$109, "B1") | H10: =G10/$G$13
A11: Environment & Sustainability | B11: =COUNTIF('Từ Vựng IELTS 6.0 - 7.0'!$A$2:$A$109, A11) | C11: =B11/$B$22 | D11: Band 6.5 - 8.0 | F11: B2 | G11: =COUNTIF('Từ Vựng IELTS 6.0 - 7.0'!$F$2:$F$109, "B2") | H11: =G11/$G$13
A12: Technology & AI | B12: =COUNTIF('Từ Vựng IELTS 6.0 - 7.0'!$A$2:$A$109, A12) | C12: =B12/$B$22 | D12: Band 6.5 - 8.0 | F12: C1 | G12: =COUNTIF('Từ Vựng IELTS 6.0 - 7.0'!$F$2:$F$109, "C1") | H12: =G12/$G$13
A13: Society & Urbanization | B13: =COUNTIF('Từ Vựng IELTS 6.0 - 7.0'!$A$2:$A$109, A13) | C13: =B13/$B$22 | D13: Band 6.5 - 7.5 | F13: Tổng cộng | G13: =SUM(G10:G12) | H13: =SUM(H10:H12)
A14: Work & Economy | B14: =COUNTIF('Từ Vựng IELTS 6.0 - 7.0'!$A$2:$A$109, A14) | C14: =B14/$B$22 | D14: Band 6.5 - 7.5
A15: Health & Well-being | B15: =COUNTIF('Từ Vựng IELTS 6.0 - 7.0'!$A$2:$A$109, A15) | C15: =B15/$B$22 | D15: Band 6.5 - 7.5
A16: Culture & Heritage | B16: =COUNTIF('Từ Vựng IELTS 6.0 - 7.0'!$A$2:$A$109, A16) | C16: =B16/$B$22 | D16: Band 7.0 - 8.0
A17: Crime & Justice | B17: =COUNTIF('Từ Vựng IELTS 6.0 - 7.0'!$A$2:$A$109, A17) | C17: =B17/$B$22 | D17: Band 6.5 - 7.5
A18: Media & Communication | B18: =COUNTIF('Từ Vựng IELTS 6.0 - 7.0'!$A$2:$A$109, A18) | C18: =B18/$B$22 | D18: Band 6.5 - 7.5
A19: Government & Policy | B19: =COUNTIF('Từ Vựng IELTS 6.0 - 7.0'!$A$2:$A$109, A19) | C19: =B19/$B$22 | D19: Band 7.0 - 8.0
A20: Tourism & Travel | B20: =COUNTIF('Từ Vựng IELTS 6.0 - 7.0'!$A$2:$A$109, A20) | C20: =B20/$B$22 | D20: Band 6.0 - 7.0
A21: Psychology & Behavior | B21: =COUNTIF('Từ Vựng IELTS 6.0 - 7.0'!$A$2:$A$109, A21) | C21: =B21/$B$22 | D21: Band 7.0 - 8.0
A22: Tổng cộng | B22: =SUM(B10:B21) | C22: =SUM(C10:C21) | D22: 12 Chủ đề toàn diện
A42: CHIẾN LƯỢC NÂNG BAND TỪ VỰNG IELTS TỪ 6.0 LÊN 7.0+ (TIÊU CHÍ LEXICAL RESOURCE)
A43: 1. Sự khác biệt then chốt giữa Band 6.0 và Band 7.0 (Lexical Resource Band Descriptors):
A44: Band 6.0: Vốn từ đầy đủ nhưng còn mang tính quen thuộc, đôi khi mắc lỗi dùng sai từ hoặc sai giới từ. Band 7.0: Sử dụng vốn từ học thuật linh hoạt, sử dụng chính xác các từ ít phổ biến (less common & idiomatic items), có nhận thức sâu sắc về phong cách kết hợp từ (collocations) và chuẩn xác về dạng từ.
A45: 2. Tối ưu hóa Collocations và Cụm từ cố định (Topic-Specific Collocations):
A46: Giám khảo chấm Writing và Speaking không đánh giá cao việc 'nhồi nhét' từ vựng đơn lẻ dài dòng. Thay vào đó, hãy sử dụng các cụm kết hợp tự nhiên (ví dụ: 'mitigate climate change', 'foster learner autonomy', 'combat juvenile delinquency', 'shrink one's carbon footprint', 'render sth obsolete').
A47: 3. Kỹ thuật Paraphrasing và kiểm soát sắc thái từ (Nuances & Connotations):
A48: Để paraphrase hiệu quả trong Writing Task 2, người học cần nắm chắc các cặp từ đồng nghĩa có cùng sắc thái biểu cảm học thuật (ví dụ: lucrative = highly remunerative; ubiquitous = omnipresent; deter = discourage; assimilate = integrate). Tránh dịch máy móc từ tiếng Việt sang tiếng Anh.
A49: 4. Nhận diện và làm chủ Họ từ (Word Families & Structural Accuracy):
A50: Mỗi khi học một danh từ, hãy mở rộng sang tính từ, động từ và trạng từ đi kèm (ví dụ: degrade -> degradation -> degraded; autonomous -> autonomy; allocate -> allocation). Dùng sai dạng từ (Word Form Error) là nguyên nhân phổ biến nhất khiến thí sinh bị giữ ở Band 6.0.
A51: 5. Ôn luyện ngắt quãng bằng Flashcard tương tác và Thực hành đặt câu:
A52: Sử dụng Tab 'Flashcard & Luyện Tập' để giải quyết 30 câu hỏi mẫu Task 2. Đánh dấu trạng thái 'Cần ôn lại' cho các từ khó nhớ và luyện tập tự viết ít nhất 2 câu luận hoàn chỉnh cho mỗi từ vựng để biến từ vựng thụ động (Passive Vocab) thành từ vựng chủ động (Active Vocab).

Sheet Flashcard & Luyện Tập
A1: BẢNG LUYỆN TẬP & ĐÁNH GIÁ MỨC ĐỘ GHI NHỚ TỪ VỰNG IELTS 6.0 - 7.0+
A2: Hướng dẫn: Tự điền từ vào chỗ trống trong các câu mẫu IELTS Writing/Speaking, sau đó đánh giá mức độ ghi nhớ ở cột 'Trạng Thái Ôn Tập' để lên kế hoạch ôn luyện định kỳ.
A4: STT | B4: Chủ Đề (Topic) | C4: Từ Cần Nhớ (Target Term) | D4: Loại Từ & Phiên Âm | E4: Định Nghĩa Tiếng Việt | F4: Câu Hỏi Luyện Tập (Điền từ vào chỗ trống) | G4: Trạng Thái Ôn Tập | H4: Ghi Chú Ôn Tập Cá Nhân
A5: 1 | B5: Education & Academic | C5: pedagogy | D5: noun | /ˈped.ə.ɡɒdʒ.i/ | E5: Phương pháp sư phạm | F5: Progressive _____ emphasizes student-centered collaboration and experiential learning over traditional rote memorization. | G5: Đã thuộc | H5: Tính từ: pedagogical approach
A6: 2 | B6: Education & Academic | C6: curriculum | D6: noun | /kəˈrɪk.jə.ləm/ | E6: Chương trình giảng dạy | F6: Educational authorities ought to incorporate practical financial literacy into the secondary school _____. | G6: Đã thuộc | H6: Số nhiều là curricula
A7: 3 | B7: Education & Academic | C7: autonomous | D7: adjective | /ɔːˈtɒn.ə.məs/ | E7: Tự chủ trong học tập | F7: Universities should cultivate _____ learners who take initiative in conducting independent academic research. | G7: Đang học | H7: Danh từ: learner autonomy
A8: 4 | B8: Environment & Sustainability | C8: biodiversity | D8: noun | /ˌbaɪ.əʊ.daɪˈvɜː.sə.ti/ | E8: Đa dạng sinh học | F8: Rampant deforestation and rising sea temperatures pose an existential threat to global marine and terrestrial _____. | G8: Đã thuộc | H8: Trọng âm 4: bi-o-di-VER-si-ty
A9: 5 | B9: Environment & Sustainability | C9: mitigate | D9: verb | /ˈmɪt.ɪ.ɡeɪt/ | E9: Làm giảm nhẹ tác hại | F9: Urgent international policies are needed to _____ the catastrophic impacts of carbon emissions on vulnerable coastlines. | G9: Đang học | H9: Trái nghĩa: exacerbate
A10: 6 | B10: Environment & Sustainability | C10: deplete | D10: verb | /dɪˈpliːt/ | E10: Làm cạn kiệt tài nguyên | F10: Overexploitation of underground aquifers will rapidly _____ precious freshwater reserves in arid regions. | G10: Đã thuộc | H10: Danh từ: resource depletion
A11: 7 | B11: Technology & AI | C11: ubiquitous | D11: adjective | /juːˈbɪk.wə.təs/ | E11: Phổ biến khắp mọi nơi | F11: Smartphones and wireless high-speed connectivity have become _____ features of modern urban civilization. | G11: Đã thuộc | H11: Đồng nghĩa: omnipresent, pervasive
A12: 8 | B12: Technology & AI | C12: disruptive | D12: adjective | /dɪsˈrʌp.tɪv/ | E12: Mang tính đột phá | F12: Generative AI is a truly _____ technology that challenges traditional employment paradigms across creative sectors. | G12: Đang học | H12: Cụm: disruptive technology / innovation
A13: 9 | B13: Technology & AI | C13: obsolete | D13: adjective | /ˌɒb.səˈliːt/ | E13: Lỗi thời, không dùng nữa | F13: Rapid advances in cloud computing have rendered physical data storage media virtually _____. | G13: Cần ôn lại | H13: Cấu trúc: render sth obsolete
A14: 10 | B14: Society & Urbanization | C14: urban sprawl | D14: noun phrase | /ˌɜː.bən ˈsprɔːl/ | E14: Đô thị hóa tự phát | F14: Uncontrolled _____ encroaches upon valuable agricultural greenbelts and strains municipal transport networks. | G14: Đã thuộc | H14: Cụm: combat / curb urban sprawl
A15: 11 | B15: Society & Urbanization | C15: gentrification | D15: noun | /ˌdʒen.trɪ.fɪˈkeɪ.ʃən/ | E15: Chỉnh trang đô thị | F15: While urban _____ revitalizes decaying infrastructure, it frequently displaces low-income long-term residents. | G15: Đang học | H15: Động từ: gentrify
A16: 12 | B16: Society & Urbanization | C16: cohesion | D16: noun | /kəʊˈhiː.ʒən/ | E16: Sự gắn kết cộng đồng | F16: Investing in accessible community cultural centers strengthens social _____ among diverse ethnic populations. | G16: Đã thuộc | H16: Tính từ: cohesive society
... A34: 30 | B34: Psychology & Behavior | C34: procrastination | D34: noun | /prəˌkræs.tɪˈneɪ.ʃən/ | E34: Thói quen trì hoãn | F34: Mastering structured time management techniques is the most effective antidote to chronic academic _____. | G34: Đã thuộc | H34: Động từ: procrastinate
