Workbook

Sheet Từ Vựng Tiếng Anh Lớp 12
A1: Topic | B1: Term | C1: PartOfSpeech | D1: Phonetic | E1: Definition | F1: CEFR | G1: Example | H1: Synonyms | I1: Antonyms | J1: Collocations | K1: Note
A2: Unit 1: Life Stories | B2: perseverance | C2: noun | D2: /ˌpɜː.sɪˈvɪə.rəns/ | E2: Sự kiên trì, bền bỉ vượt qua muôn vàn gian nan thử thách | F2: B2 | G2: Through extraordinary perseverance and dedication, Marie Curie made historic breakthroughs in radioactivity. | H2: persistence, tenacity, endurance, determination | I2: giving up, surrender, apathy | J2: show perseverance, through sheer perseverance, perseverance in the face of obstacles | K2: Động từ là 'persevere' /ˌpɜː.sɪˈvɪər/ (persevere in/with something).
A3: Unit 1: Life Stories | B3: distinguished | C3: adjective | D3: /dɪˈstɪŋ.ɡwɪʃt/ | E3: Kiệt xuất, lỗi lạc, được kính trọng bởi sự nghiệp vĩ đại | F3: B2 | G3: General Vo Nguyen Giap was a distinguished military strategist admired across the globe. | H3: eminent, illustrious, celebrated, renowned | I3: unknown, obscure, ordinary, undistinguished | J3: distinguished career, distinguished scholar, distinguished guest, highly distinguished | K3: Phân biệt: 'distinguished' (lỗi lạc) và 'distinguishable' (có thể phân biệt được).
A4: Unit 1: Life Stories | B4: philanthropist | C4: noun | D4: /fɪˈlæn.θrə.pɪst/ | E4: Nhà từ thiện, người giàu lòng nhân ái hiến tặng tài sản giúp đời | F4: C1 | G4: The tech billionaire became a full-time philanthropist dedicated to eradicating infectious diseases. | H4: benefactor, humanitarian, patron, donor | I4: miser, misanthrope | J4: generous philanthropist, billionaire philanthropist, noted philanthropist | K4: Danh từ trừu tượng: 'philanthropy' (hoạt động nhân đạo từ thiện). Trọng âm 2.
A5: Unit 1: Life Stories | B5: legacy | C5: noun | D5: /ˈleɡ.ə.si/ | E5: Di sản tinh thần hoặc vật chất để lại cho thế hệ sau | F5: B2 | G5: President Ho Chi Minh left an enduring legacy of patriotism and moral integrity for the nation. | H5: heritage, bequest, inheritance, endowment | I5: N/A | J5: leave a legacy, enduring legacy, lasting legacy, rich legacy | K5: Số nhiều: legacies. Thành ngữ: 'legacy of something'.
A6: Unit 1: Life Stories | B6: overcome adversity | C6: verb phrase | D6: /ˌəʊ.vəˈkʌm ədˈvɜː.sə.ti/ | E6: Vượt qua nghịch cảnh, chiến thắng những hoàn cảnh ngặt nghèo nhất | F6: C1 | G6: Nick Vujicic inspired millions by demonstrating how courage helps individuals overcome adversity. | H6: triumph over hardship, conquer difficulties | I6: succumb to hardship, yield to despair | J6: courage to overcome adversity, overcome severe adversity, resilience in adversity | K6: 'Adversity' (nghịch cảnh) khác với 'adversary' (kẻ thù/đối thủ).
A7: Unit 1: Life Stories | B7: prestigious | C7: adjective | D7: /presˈtɪdʒ.əs/ | E7: Danh giá, có uy tín và thanh thế lẫy lừng | F7: B2 | G7: Professor Ngo Bao Chau was awarded the prestigious Fields Medal in mathematics in 2010. | H7: reputable, esteemed, distinguished, high-status | I7: disreputable, obscure, insignificant | J7: prestigious award, prestigious university, prestigious scholarship | K7: Danh từ là 'prestige' /presˈtiːʒ/ (uy tín, thanh thế). Trọng âm 2.
A8: Unit 2: A Multicultural World | B8: cultural assimilation | C8: noun phrase | D8: /ˌkʌl.tʃər.əl əˌsɪm.ɪˈleɪ.ʃən/ | E8: Sự đồng hóa văn hóa (quá trình tiếp thu hoàn toàn văn hóa của cộng đồng đa số) | F8: C1 | G8: Immigrants often experience pressure toward cultural assimilation while trying to maintain their mother tongue. | H8: cultural absorption, cultural integration | I8: cultural preservation, cultural segregation | J8: force cultural assimilation, process of cultural assimilation, rapid assimilation | K8: Động từ: 'assimilate into' (đồng hóa, hòa nhập vào).
A9: Unit 2: A Multicultural World | B9: acculturation | C9: noun | D9: /əˌkʌl.tʃəˈreɪ.ʃən/ | E9: Sự tiếp biến văn hóa (sự biến đổi văn hóa khi hai nền văn hóa tiếp xúc lâu dài) | F9: C1 | G9: Acculturation allows individuals to adopt values from a new host society while preserving native traditions. | H9: cultural adaptation, intercultural exchange | I9: cultural alienation, ethnocentrism | J9: process of acculturation, levels of acculturation, cross-cultural acculturation | K9: Thuật ngữ nhân học văn hóa nâng cao xuất hiện trong các bài đọc hiểu chuyên sâu.
A10: Unit 2: A Multicultural World | B10: cultural identity | C10: noun phrase | D10: /ˌkʌl.tʃər.əl aɪˈden.tə.ti/ | E10: Bản sắc văn hóa (những nét đặc trưng định hình nên một dân tộc/cộng đồng) | F10: B2 | G10: Traditional festivals and the national costume Ao Dai play an essential role in safeguarding our cultural identity. | H10: cultural distinctiveness, national identity | I10: cultural homogenization | J10: preserve cultural identity, retain cultural identity, shape cultural identity, loss of identity | K10: Động từ: 'identify with' (đồng nhất, nhận diện với).
A11: Unit 2: A Multicultural World | B11: melting pot | C11: noun phrase | D11: /ˈmel.tɪŋ ˌpɒt/ | E11: Nồi lẩu văn hóa (nơi giao thoa và hòa trộn nhiều sắc tộc, nền văn hóa khác nhau) | F11: C1 | G11: New York City is often referred to as a vibrant melting pot of global cultures and cuisines. | H11: cultural mosaic, multicultural society, cosmopolitan center | I11: monocultural society, homogeneous community | J11: cultural melting pot, dynamic melting pot, urban melting pot | K11: Phân biệt với mô hình 'salad bowl' (các nền văn hóa cùng tồn tại nhưng giữ nguyên bản sắc riêng).
A12: Unit 2: A Multicultural World | B12: ethnocentrism | C12: noun | D12: /ˌeθ.nəʊˈsen.trɪ.zəm/ | E12: Chủ nghĩa vị chủng (thái độ cho rằng văn hóa dân tộc mình là ưu việt hơn tất cả) | F12: C1 | G12: Education must combat ethnocentrism by teaching empathy and cross-cultural appreciation. | H12: cultural superiority, cultural chauvinism, xenophobia | I12: cultural relativism, cosmopolitanism, open-mindedness | J12: overcome ethnocentrism, danger of ethnocentrism, ethnocentric attitude | K12: Tính từ: 'ethnocentric' /ˌeθ.nəʊˈsen.trɪk/.
... A61: Unit 10: Lifelong Learning | B61: critical thinking | C61: noun phrase | D61: /ˌkrɪt.ɪ.kəl ˈθɪŋ.kɪŋ/ | E61: Tư duy phản biện (năng lực phân tích, đánh giá thông tin một cách khách quan và logic) | F61: B2 | G61: Higher education places a heavy emphasis on developing students' critical thinking and analytical reasoning. | H61: analytical thinking, rational inquiry, objective reasoning | I61: blind acceptance, irrational belief | J61: develop critical thinking, critical thinking skills, foster critical thinking | K61: Kỹ năng thế kỷ 21 hàng đầu dành cho học sinh chuẩn bị vào đại học.

Sheet Tổng Quan & Thống Kê
A1: TỔNG HỢP VÀ PHÂN TÍCH TỪ VỰNG TIẾNG ANH LỚP 12
A2: Hệ thống từ vựng học thuật chuẩn hóa 10 Unit GDPT 2018 (Global Success, Friends Global, Bright, i-Learn Smart World) phục vụ ôn thi Tốt nghiệp THPT, ĐGNL & IELTS
B4: TỔNG SỐ TỪ VỰNG | D4: SỐ CHỦ ĐỀ (UNITS) | F4: TRÌNH ĐỘ B2 (UPPER-INTER) | H4: TRÌNH ĐỘ C1 (ADVANCED)
B5: =COUNTA('Từ Vựng Tiếng Anh Lớp 12'!B2:B61) | D5: 10 | F5: =COUNTIF('Từ Vựng Tiếng Anh Lớp 12'!F2:F61, "B2") | H5: =COUNTIF('Từ Vựng Tiếng Anh Lớp 12'!F2:F61, "C1")
A8: BẢNG 1: THỐNG KÊ TỪ VỰNG THEO TỪNG CHỦ ĐỀ LỚP 12 | F8: BẢNG 2: PHÂN BỐ THEO TRÌNH ĐỘ CEFR
A9: Mã & Tên Chủ Đề | B9: Số Từ Vựng | C9: Tỷ Lệ (%) | D9: Cấp Độ Mục Tiêu | F9: Cấp Độ CEFR | G9: Số Từ Vựng | H9: Tỷ Lệ (%)
A10: Unit 1: Life Stories | B10: =COUNTIF('Từ Vựng Tiếng Anh Lớp 12'!$A$2:$A$61, A10) | C10: =B10/$B$20 | D10: B2 - C1 | F10: B1 | G10: =COUNTIF('Từ Vựng Tiếng Anh Lớp 12'!$F$2:$F$61, "B1") | H10: =G10/$G$13
A11: Unit 2: A Multicultural World | B11: =COUNTIF('Từ Vựng Tiếng Anh Lớp 12'!$A$2:$A$61, A11) | C11: =B11/$B$20 | D11: B2 - C1 | F11: B2 | G11: =COUNTIF('Từ Vựng Tiếng Anh Lớp 12'!$F$2:$F$61, "B2") | H11: =G11/$G$13
A12: Unit 3: Green Living | B12: =COUNTIF('Từ Vựng Tiếng Anh Lớp 12'!$A$2:$A$61, A12) | C12: =B12/$B$20 | D12: B1 - C1 | F12: C1 | G12: =COUNTIF('Từ Vựng Tiếng Anh Lớp 12'!$F$2:$F$61, "C1") | H12: =G12/$G$13
A13: Unit 4: Urbanisation | B13: =COUNTIF('Từ Vựng Tiếng Anh Lớp 12'!$A$2:$A$61, A13) | C13: =B13/$B$20 | D13: B2 - C1 | F13: Tổng cộng | G13: =SUM(G10:G12) | H13: =SUM(H10:H12)
A14: Unit 5: The World of Work | B14: =COUNTIF('Từ Vựng Tiếng Anh Lớp 12'!$A$2:$A$61, A14) | C14: =B14/$B$20 | D14: B2 - C1
A15: Unit 6: Artificial Intelligence | B15: =COUNTIF('Từ Vựng Tiếng Anh Lớp 12'!$A$2:$A$61, A15) | C15: =B15/$B$20 | D15: B2 - C1
A16: Unit 7: World of Mass Media | B16: =COUNTIF('Từ Vựng Tiếng Anh Lớp 12'!$A$2:$A$61, A16) | C16: =B16/$B$20 | D16: B2 - C1
A17: Unit 8: Wildlife Conservation | B17: =COUNTIF('Từ Vựng Tiếng Anh Lớp 12'!$A$2:$A$61, A17) | C17: =B17/$B$20 | D17: B2 - C1
A18: Unit 9: Career Paths | B18: =COUNTIF('Từ Vựng Tiếng Anh Lớp 12'!$A$2:$A$61, A18) | C18: =B18/$B$20 | D18: B2 - C1
A19: Unit 10: Lifelong Learning | B19: =COUNTIF('Từ Vựng Tiếng Anh Lớp 12'!$A$2:$A$61, A19) | C19: =B19/$B$20 | D19: B1 - C1
A20: Tổng cộng | B20: =SUM(B10:B19) | C20: =SUM(C10:C19) | D20: Toàn bộ 10 Units
A40: CHIẾN LƯỢC ÔN TẬP TỪ VỰNG TIẾNG ANH LỚP 12 - CHINH PHỤC ĐIỂM 9-10 THPT QUỐC GIA & IELTS 7.0+
A41: 1. Làm chủ các chủ đề đọc hiểu phân loại cao (High-Level Reading Topics):
A42: Các bài đọc hiểu phân loại 9+ trong kỳ thi Tốt nghiệp THPT và kỳ thi Đánh giá năng lực (ĐGNL) thường xoay quanh: Trí tuệ nhân tạo (AI & Machine Learning), Kinh tế tuần hoàn & Khủng hoảng khí hậu, Đô thị hóa và Thách thức việc làm tương lai. Nắm chắc vốn từ vựng trong file này giúp học sinh tăng 40-50% tốc độ đọc hiểu.
A43: 2. Tuyệt đối không học từ vựng riêng lẻ - Phải học theo Collocations & Prepositions:
A44: Hơn 60% câu hỏi từ vựng trong đề thi trắc nghiệm kiểm tra khả năng kết hợp từ (ví dụ: 'overcome adversity', 'bridge the divide', 'deplete natural resources', 'curriculum vitae', 'autonomous learner'). Việc thuộc cả cụm từ giúp chọn đáp án chính xác trong vòng 5 giây.
A45: 3. Chiến lược bẫy từ đồng nghĩa / trái nghĩa (Synonyms & Antonyms Trap):
A46: Đề thi chính thức thường cài bẫy các từ có vẻ giống nhau nhưng khác sắc thái biểu cảm. Hãy luyện tập kỹ các cặp từ tương phản (ví dụ: 'ethnocentrism' >< 'cosmopolitanism'; 'deplete' >< 'replenish'; 'lucrative' >< 'unprofitable').
A47: 4. Rèn luyện kỹ thuật đoán nghĩa từ ngữ cảnh (Contextual Guessing):
A48: Học sinh lớp 12 cần rèn luyện phản xạ nhận diện từ nối (Linking words) như 'although, however, in contrast, consequently' để suy luận nghĩa của các từ vựng C1 khó khi làm bài thi mà không cần từ điển.
A49: 5. Ôn tập ngắt quãng với Flashcard & Tự đánh giá định kỳ:
A50: Sử dụng Tab 'Flashcard & Luyện Tập' để giải quyết các câu trắc nghiệm thực chiến, đổi màu trạng thái thành 'Cần ôn lại' cho những từ hay quên để tập trung ôn luyện vào các tuần nước rút trước kỳ thi.

Sheet Flashcard & Luyện Tập
A1: BẢNG LUYỆN TẬP & ĐÁNH GIÁ MỨC ĐỘ GHI NHỚ TỪ VỰNG TIẾNG ANH LỚP 12
A2: Hướng dẫn: Tự điền từ vào chỗ trống trong câu, sau đó đánh giá mức độ ghi nhớ ở cột 'Trạng Thái Ôn Tập' để lên kế hoạch ôn luyện nước rút trước kỳ thi.
A4: STT | B4: Chủ Đề (Topic) | C4: Từ Cần Nhớ (Target Term) | D4: Loại Từ & Phiên Âm | E4: Định Nghĩa Tiếng Việt | F4: Câu Hỏi Luyện Tập (Điền từ vào chỗ trống) | G4: Trạng Thái Ôn Tập | H4: Ghi Chú Ôn Tập Cá Nhân
A5: 1 | B5: Unit 1: Life Stories | C5: perseverance | D5: noun | /ˌpɜː.sɪˈvɪə.rəns/ | E5: Sự kiên trì, bền bỉ | F5: It was through sheer determination and unwavering _____ that she completed her medical doctorate despite financial hardship. | G5: Đã thuộc | H5: Động từ là persevere in/with
A6: 2 | B6: Unit 1: Life Stories | C6: overcome adversity | D6: verb phrase | /ˌəʊ.vəˈkʌm ədˈvɜː.sə.ti/ | E6: Vượt qua nghịch cảnh | F6: The autobiographies of great leaders teach us how human resilience helps individuals _____ and achieve greatness. | G6: Đã thuộc | H6: Phân biệt adversity (nghịch cảnh) & adversary (đối thủ)
A7: 3 | B7: Unit 2: A Multicultural World | C7: cultural assimilation | D7: noun phrase | /ˌkʌl.tʃər.əl əˌsɪm.ɪˈleɪ.ʃən/ | E7: Sự đồng hóa văn hóa | F7: While integrating into a new society, immigrants often resist complete _____ to protect their unique heritage. | G7: Đang học | H7: Động từ assimilate into
A8: 4 | B8: Unit 2: A Multicultural World | C8: ethnocentrism | D8: noun | /ˌeθ.nəʊˈsen.trɪ.zəm/ | E8: Chủ nghĩa vị chủng | F8: Global education programs encourage cultural empathy and help students eliminate narrow-minded _____. | G8: Cần ôn lại | H8: Tính từ là ethnocentric
A9: 5 | B9: Unit 2: A Multicultural World | C9: melting pot | D9: noun phrase | /ˈmel.tɪŋ ˌpɒt/ | E9: Nồi lẩu văn hóa giao thoa | F9: London has long been regarded as a vibrant cultural _____ where dozens of global languages and traditions thrive. | G9: Đã thuộc | H9: Phân biệt với mô hình salad bowl
A10: 6 | B10: Unit 3: Green Living | C10: circular economy | D10: noun phrase | /ˌsɜː.kjə.lər iˈkɒn.ə.mi/ | E10: Kinh tế tuần hoàn | F10: Transitioning towards a _____ allows industrial manufacturers to eliminate plastic waste by redesigning recyclable materials. | G10: Đã thuộc | H10: Đối lập với linear economy
A11: 7 | B11: Unit 3: Green Living | C11: carbon neutral | D11: adjective | /ˌkɑː.bən ˈnjuː.trəl/ | E11: Trung hòa carbon | F11: Tech corporations have set ambitious commitments to become completely _____ by switching to 100% solar and wind power. | G11: Đã thuộc | H11: Danh từ là carbon neutrality
A12: 8 | B12: Unit 3: Green Living | C12: deplete | D12: verb | /dɪˈpliːt/ | E12: Làm cạn kiệt tài nguyên | F12: Excessive overconsumption of fossil fuels will rapidly _____ finite global energy reserves within a few decades. | G12: Đang học | H12: Danh từ resource depletion
A13: 9 | B13: Unit 4: Urbanisation | C13: urban sprawl | D13: noun phrase | /ˌɜː.bən ˈsprɔːl/ | E13: Mở rộng đô thị tràn lan | F13: Unchecked _____ encroaches on fertile greenbelts and puts immense pressure on metropolitan public transportation. | G13: Đang học | H13: Cụm combat urban sprawl
A14: 10 | B14: Unit 4: Urbanisation | C14: rural-to-urban migration | D14: noun phrase | /ˌrʊə.rəl tu ˈɜː.bən maɪˈɡreɪ.ʃən/ | E14: Di cư từ nông thôn ra phố | F14: The unprecedented wave of _____ has led to acute housing shortages and overcrowded public hospitals in megacities. | G14: Đã thuộc | H14: Danh từ chỉ người: migrant
A15: 11 | B15: Unit 4: Urbanisation | C15: sanitation | D15: noun | /ˌsæn.ɪˈteɪ.ʃən/ | E15: Vệ sinh môi trường công cộng | F15: Investing in clean water and modern sewage _____ is vital to prevent epidemic outbreaks in densely packed slums. | G15: Đã thuộc | H15: Tính từ là sanitary >< unsanitary
A16: 12 | B16: Unit 5: The World of Work | C16: adaptability | D16: noun | /əˌdæp.təˈbɪl.ə.ti/ | E16: Khả năng thích ứng linh hoạt | F16: Given the rapid disruption of digital automation, workplace _____ is the most prized asset of modern employees. | G16: Đã thuộc | H16: Động từ adapt to + N/V-ing
... A29: 25 | B29: Unit 10: Lifelong Learning | C29: autonomous learner | D29: noun phrase | /ɔːˈtɒn.ə.məs ˈlɜː.nər/ | E29: Người học tự chủ | F29: To excel in tertiary education, undergraduates must transform themselves into self-directed and _____. | G29: Đã thuộc | H29: Danh từ learner autonomy
