Workbook

Sheet Từ Vựng IELTS 7.0 - 8.0
A1: Topic | B1: Term | C1: PartOfSpeech | D1: Phonetic | E1: Definition | F1: CEFR | G1: Example | H1: Synonyms | I1: Antonyms | J1: Collocations | K1: Note
A2: Education & Intellectual Inquiry | B2: pedagogical | C2: adjective | D2: /ˌped.əˈɡɒdʒ.ɪ.kəl/ | E2: Thuộc về phương pháp sư phạm, nghệ thuật và lý thuyết giảng dạy | F2: C1 | G2: Progressive pedagogical frameworks prioritize active inquiry and collaborative problem-solving over passive rote learning. | H2: didactic, instructional, educational, academic | I2: non-instructional | J2: pedagogical approach, pedagogical methods, pedagogical innovation, pedagogical framework | K2: Danh từ: pedagogy /ˈped.ə.ɡɒdʒ.i/. Rất hiệu quả khi phân tích phương pháp giáo dục trong Writing Task 2.
A3: Education & Intellectual Inquiry | B3: delineate | C3: verb | D3: /dɪˈlɪn.i.eɪt/ | E3: Phác thảo, mô tả hoặc phân định ranh giới một cách chi tiết, chính xác | F3: C1 | G3: The revised academic curriculum clearly delineates the specific learning outcomes and assessment criteria for each module. | H3: demarcate, outline, define, articulate, specify | I3: confuse, obscure, blur, distort | J3: clearly delineate, delineate boundaries, delineate responsibilities | K3: Danh từ: delineation /dɪˌlɪn.iˈeɪ.ʃən/. Dùng thay cho 'describe clearly' hoặc 'set boundaries'.
A4: Education & Intellectual Inquiry | B4: erudite | C4: adjective | D4: /ˈer.uː.daɪt/ | E4: Uyên bác, thông thái, có học vấn sâu rộng nhờ dày công nghiên cứu | F4: C2 | G4: The professor delivered an erudite lecture examining the epistemological foundations of classical philosophy. | H4: scholarly, learned, profound, knowledgeable, intellectual | I4: ignorant, uneducated, illiterate, shallow | J4: erudite scholar, erudite commentary, erudite lecture, highly erudite | K4: Danh từ: erudition /ˌer.uːˈdɪʃ.ən/ (sự uyên bác). Từ C2 ăn điểm cực cao trong Speaking Part 3.
A5: Education & Intellectual Inquiry | B5: didactic | C5: adjective | D5: /daɪˈdæk.tɪk/ | E5: Mang tính giáo huấn, có chủ đích răn dạy đạo đức hoặc truyền thụ kiến thức | F5: C1 | G5: Traditional children's literature often employs overtly didactic narratives to instill civic virtues. | H5: instructive, moralistic, educational, pedagogic | I5: uninstructive, entertaining, non-moralizing | J5: didactic literature, didactic purpose, didactic tone, didactic approach | K5: Đôi khi mang sắc thái tiêu cực nhẹ nếu việc giáo huấn quá cứng nhắc hoặc giáo điều.
A6: Education & Intellectual Inquiry | B6: epistemology | C6: noun | D6: /ɪˌpɪs.təˈmɒl.ə.dʒi/ | E6: Nhận thức luận (phân ngành triết học nghiên cứu về bản chất, nguồn gốc và giới hạn của tri thức) | F6: C2 | G6: The transition to digital learning environments has compelled educators to re-examine traditional epistemology. | H6: theory of knowledge, cognitive philosophy | I6: N/A | J6: epistemological framework, branch of epistemology, epistemological inquiry | K6: Tính từ: epistemological /ɪˌpɪs.tə.məˈlɒdʒ.ɪ.kəl/. Thuật ngữ triết học học thuật đỉnh cao.
A7: Education & Intellectual Inquiry | B7: disseminate | C7: verb | D7: /dɪˈsem.ɪ.neɪt/ | E7: Phổ biến, truyền bá rộng rãi thông tin, tri thức hoặc tư tưởng | F7: C1 | G7: Open-access digital repositories enable academic institutions to disseminate peer-reviewed research globally. | H7: promulgate, distribute, circulate, broadcast, propagate | I7: suppress, withhold, conceal, restrict | J7: disseminate information, disseminate knowledge, widely disseminate | K7: Danh từ: dissemination /dɪˌsem.ɪˈneɪ.ʃən/. Dùng thay thế hoàn hảo cho 'spread information'.
A8: Education & Intellectual Inquiry | B8: stifle | C8: verb | D8: /ˈstaɪ.fəl/ | E8: Kìm hãm, dập tắt, bóp nghẹt sự sáng tạo hoặc tư duy độc lập | F8: C1 | G8: Excessive emphasis on standardized testing risks stifling students' intellectual curiosity and original thinking. | H8: suppress, inhibit, suffocate, quell, repress | I8: foster, nurture, cultivate, stimulate, encourage | J8: stifle creativity, stifle innovation, stifle debate, stifle curiosity | K8: Thường dùng trong các lập luận phản đối giáo dục rập khuôn: 'stifle critical thinking'.
A9: Education & Intellectual Inquiry | B9: paradigm shift | C9: noun phrase | D9: /ˈpær.ə.daɪm ʃɪft/ | E9: Sự chuyển dịch hệ hình (sự thay đổi căn bản trong nhận thức và phương thức tiếp cận một lĩnh vực) | F9: C1 | G9: The integration of generative artificial intelligence represents a profound paradigm shift in educational delivery. | H9: fundamental transformation, radical change, conceptual revolution | I9: status quo, incremental adjustment | J9: trigger a paradigm shift, profound paradigm shift, witness a paradigm shift | K9: Phát âm: /ˈpær.ə.daɪm/ (chữ 'g' câm). Thuật ngữ học thuật nổi tiếng của Thomas Kuhn.
A10: Education & Intellectual Inquiry | B10: holistic | C10: adjective | D10: /həʊˈlɪs.tɪk/ | E10: Toàn diện, tổng thể (xem xét mọi khía cạnh liên kết hữu cơ thay vì phân mảnh) | F10: C1 | G10: Adopting a holistic pedagogical approach ensures that learners develop emotional intelligence alongside academic acumen. | H10: comprehensive, integrated, all-encompassing, exhaustive | I10: atomistic, fragmented, piecemeal, compartmentalized | J10: holistic approach, holistic assessment, holistic view, holistic education | K10: Dùng cực kỳ ấn tượng trong câu kết bài hoặc phần đề xuất giải pháp bài Writing Task 2.
A11: Environment & Climate Crisis | B11: anthropogenic | C11: adjective | D11: /ˌæn.θrə.pəˈdʒen.ɪk/ | E11: Do con người gây ra, có nguồn gốc từ các hoạt động của nhân loại | F11: C1 | G11: Scientific consensus overwhelmingly attributes the accelerating rate of global warming to anthropogenic emissions. | H11: human-induced, human-caused, artificial | I11: natural, biogenic, non-anthropogenic | J11: anthropogenic climate change, anthropogenic emissions, anthropogenic activities | K11: Anthropo- (con người) + -genic (sinh ra/gây ra). Cụm từ chuẩn học thuật thay cho 'caused by humans'.
A12: Environment & Climate Crisis | B12: exacerbate | C12: verb | D12: /ɪɡˈzæs.ə.beɪt/ | E12: Làm trầm trọng thêm, khiến một tình trạng vốn đã xấu trở nên tồi tệ hơn | F12: C1 | G12: Severe deforestation exacerbates topsoil erosion, rendering coastal regions acutely vulnerable to flash floods. | H12: aggravate, worsen, intensify, inflame, compound | I12: mitigate, alleviate, ameliorate, relieve | J12: exacerbate the problem, exacerbate tensions, exacerbate climate change | K12: Trọng âm 2. Từ vựng C1 cốt lõi trong Writing Task 2 để phân tích nguyên nhân - hậu quả.
... A109: Psychology & Human Behavior | B109: altruism | C109: noun | D109: /ˈæl.tru.ɪ.zəm/ | E109: Lòng vị tha, hành động cống hiến quên mình vì lợi ích của người khác | F109: C1 | G109: Evolutionary biologists investigate whether pure altruism exists or if cooperative behaviors offer mutual survival benefits. | H109: selflessness, philanthropy, benevolence, generosity, unselfishness | I109: egoism, selfishness, narcissism, self-interest | J109: pure altruism, act of altruism, reciprocal altruism | K109: Tính từ: altruistic /ˌæl.truˈɪs.tɪk/. Trái nghĩa: egoism / selfishness.

Sheet Tổng Quan & Thống Kê
A1: TỔNG HỢP VÀ PHÂN TÍCH TỪ VỰNG HỌC THUẬT IELTS BAND 7.0 - 8.0+
A2: Hệ thống 108+ thuật ngữ học thuật chuyên sâu (C1-C2 Academic Lexicon) tối ưu cho mục tiêu bứt phá Lexical Resource Band 7.5 - 8.5+ trong IELTS Writing Task 2 & Speaking Part 3
B4: TỔNG SỐ TỪ VỰNG | D4: SỐ CHỦ ĐỀ CHUYÊN SÂU | F4: TRÌNH ĐỘ C1 (ADVANCED) | H4: TRÌNH ĐỘ C2 (PROFICIENCY)
B5: =COUNTA('Từ Vựng IELTS 7.0 - 8.0'!B2:B109) | D5: 12 | F5: =COUNTIF('Từ Vựng IELTS 7.0 - 8.0'!F2:F109, "C1") | H5: =COUNTIF('Từ Vựng IELTS 7.0 - 8.0'!F2:F109, "C2")
A8: BẢNG 1: PHÂN BỐ TỪ VỰNG THEO 12 CHỦ ĐỀ HỌC THUẬT NÂNG CAO | F8: BẢNG 2: PHÂN BỐ THEO TRÌNH ĐỘ CEFR
A9: Mã & Tên Chủ Đề | B9: Số Từ Vựng | C9: Tỷ Lệ (%) | D9: Mục Tiêu IELTS | F9: Cấp Độ CEFR | G9: Số Từ Vựng | H9: Tỷ Lệ (%)
A10: Education & Intellectual Inquiry | B10: =COUNTIF('Từ Vựng IELTS 7.0 - 8.0'!$A$2:$A$109, A10) | C10: =B10/$B$22 | D10: Band 7.5 - 8.5 | F10: B2 | G10: =COUNTIF('Từ Vựng IELTS 7.0 - 8.0'!$F$2:$F$109, "B2") | H10: =G10/$G$13
A11: Environment & Climate Crisis | B11: =COUNTIF('Từ Vựng IELTS 7.0 - 8.0'!$A$2:$A$109, A11) | C11: =B11/$B$22 | D11: Band 7.5 - 8.5 | F11: C1 | G11: =COUNTIF('Từ Vựng IELTS 7.0 - 8.0'!$F$2:$F$109, "C1") | H11: =G11/$G$13
A12: Technology & AI | B12: =COUNTIF('Từ Vựng IELTS 7.0 - 8.0'!$A$2:$A$109, A12) | C12: =B12/$B$22 | D12: Band 7.5 - 8.5 | F12: C2 | G12: =COUNTIF('Từ Vựng IELTS 7.0 - 8.0'!$F$2:$F$109, "C2") | H12: =G12/$G$13
A13: Society & Urbanization | B13: =COUNTIF('Từ Vựng IELTS 7.0 - 8.0'!$A$2:$A$109, A13) | C13: =B13/$B$22 | D13: Band 7.5 - 8.5 | F13: Tổng cộng | G13: =SUM(G10:G12) | H13: =SUM(H10:H12)
A14: Economy & Labor Market | B14: =COUNTIF('Từ Vựng IELTS 7.0 - 8.0'!$A$2:$A$109, A14) | C14: =B14/$B$22 | D14: Band 7.5 - 8.5
A15: Health & Bioethics | B15: =COUNTIF('Từ Vựng IELTS 7.0 - 8.0'!$A$2:$A$109, A15) | C15: =B15/$B$22 | D15: Band 7.5 - 8.5
A16: Culture & Globalization | B16: =COUNTIF('Từ Vựng IELTS 7.0 - 8.0'!$A$2:$A$109, A16) | C16: =B16/$B$22 | D16: Band 7.5 - 8.5
A17: Crime & Penal Policy | B17: =COUNTIF('Từ Vựng IELTS 7.0 - 8.0'!$A$2:$A$109, A17) | C17: =B17/$B$22 | D17: Band 7.5 - 8.5
A18: Media & Public Discourse | B18: =COUNTIF('Từ Vựng IELTS 7.0 - 8.0'!$A$2:$A$109, A18) | C18: =B18/$B$22 | D18: Band 7.5 - 8.5
A19: Government & Public Policy | B19: =COUNTIF('Từ Vựng IELTS 7.0 - 8.0'!$A$2:$A$109, A19) | C19: =B19/$B$22 | D19: Band 7.5 - 8.5
A20: Tourism & Conservation | B20: =COUNTIF('Từ Vựng IELTS 7.0 - 8.0'!$A$2:$A$109, A20) | C20: =B20/$B$22 | D20: Band 7.0 - 8.0
A21: Psychology & Human Behavior | B21: =COUNTIF('Từ Vựng IELTS 7.0 - 8.0'!$A$2:$A$109, A21) | C21: =B21/$B$22 | D21: Band 7.5 - 8.5
A22: Tổng cộng | B22: =SUM(B10:B21) | C22: =SUM(C10:C21) | D22: 12 Chủ đề nâng cao
A42: CHIẾN THUẬT LÀM CHỦ TỪ VỰNG HỌC THUẬT BỨT PHÁ BAND 7.0 LÊN 8.0+ (TIÊU CHÍ LEXICAL RESOURCE)
A43: 1. Sự khác biệt mang tính quyết định giữa Band 7.0 và Band 8.0+ (Lexical Precision & Sophistication):
A44: Band 7.0 sử dụng từ vựng nâng cao có nhận thức về collocation nhưng vẫn có thể xuất hiện sự gượng ép nhỏ (occasional inaccuracies). Band 8.0+ sử dụng vốn từ linh hoạt, chuẩn xác tuyệt đối về sắc thái ngữ nghĩa (nuances & register), kết hợp tự nhiên các cấu trúc ít phổ biến (uncommon lexical items) và hoàn toàn không mắc lỗi dùng sai từ.
A45: 2. Sử dụng Collocations học thuật C1-C2 tự nhiên thay vì nhồi nhét từ đơn lẻ (Natural Academic Phrasing):
A46: Giám khảo chấm IELTS đánh giá cao sự kết hợp chuẩn xác mang tính chuyên gia (ví dụ: 'exacerbate socio-economic disparities', 'mitigate cataclysmic climate risks', 'harness the demographic dividend', 'foster durable social cohesion', 'practicing planned obsolescence'). Tránh ghép từ dịch thô từ tiếng Việt.
A47: 3. Kiểm soát sắc thái ngữ nghĩa và phong cách học thuật (Nuances & Formal Register):
A48: Hiểu rõ sự phân hóa giữa các từ tưởng chừng tương đồng: 'misinformation' (tin sai vô ý) vs 'disinformation' (tin giả có toan tính); 'acculturation' (tiếp biến giữ bản sắc) vs 'assimilation' (đồng hóa hòa tan); 'mitigate' (giảm nhẹ tác hại) vs 'ameliorate' (cải thiện nâng cấp tình hình).
A49: 4. Phát triển kỹ năng Paraphrasing đỉnh cao trong Writing Task 2 & Speaking Part 3:
A50: Sử dụng linh hoạt các biến thể từ vựng đồng nghĩa học thuật (ví dụ: lucrative = highly remunerative; ubiquitous = omnipresent; erode = undermine; deteriorate = degrade) để tránh lặp từ và thể hiện chiều sâu tư duy phân tích.
A51: 5. Luyện tập tương tác và kích hoạt từ vựng chủ động (Active Vocabulary Activation):
A52: Làm bài kiểm tra tại Tab 'Flashcard & Luyện Tập'. Đối với mỗi thuật ngữ C1/C2, hãy tự viết 2 câu luận hoàn chỉnh (một câu nêu nguyên nhân, một câu nêu giải pháp) để biến từ vựng thành phản xạ tự nhiên trong phòng thi.

Sheet Flashcard & Luyện Tập
A1: BẢNG LUYỆN TẬP & ĐÁNH GIÁ MỨC ĐỘ GHI NHỚ TỪ VỰNG IELTS 7.0 - 8.0+
A2: Hướng dẫn: Tự điền từ vào chỗ trống trong các câu mẫu IELTS Writing Task 2 & Speaking Part 3, sau đó đánh giá mức độ ghi nhớ ở cột 'Trạng Thái Ôn Tập' để lên kế hoạch ôn luyện nước rút.
A4: STT | B4: Chủ Đề (Topic) | C4: Từ Cần Nhớ (Target Term) | D4: Loại Từ & Phiên Âm | E4: Định Nghĩa Tiếng Việt | F4: Câu Hỏi Luyện Tập (Điền từ vào chỗ trống) | G4: Trạng Thái Ôn Tập | H4: Ghi Chú Ôn Tập Cá Nhân
A5: 1 | B5: Education & Intellectual Inquiry | C5: pedagogical | D5: adj | /ˌped.əˈɡɒdʒ.ɪ.kəl/ | E5: Thuộc phương pháp sư phạm | F5: Progressive _____ frameworks prioritize active inquiry and collaborative problem-solving over passive memorization. | G5: Đã thuộc | H5: Danh từ: pedagogy / Cụm: pedagogical approach
A6: 2 | B6: Education & Intellectual Inquiry | C6: delineate | D6: verb | /dɪˈlɪn.i.eɪt/ | E6: Phác thảo, phân định rõ ràng | F6: The revised academic syllabus clearly _____ the specific learning outcomes and grading rubrics for each seminar. | G6: Đang học | H6: Đồng nghĩa: demarcate, define precisely
A7: 3 | B7: Education & Intellectual Inquiry | C7: erudite | D7: adj | /ˈer.uː.daɪt/ | E7: Uyên bác, học vấn sâu rộng | F7: The visiting professor delivered an _____ lecture dissecting the philosophical foundations of modern bioethics. | G7: Cần ôn lại | H7: Danh từ: erudition (từ C2 ấn tượng)
A8: 4 | B8: Environment & Climate Crisis | C8: anthropogenic | D8: adj | /ˌæn.θrə.pəˈdʒen.ɪk/ | E8: Do con người gây ra | F8: Climatologists overwhelmingly attribute the rapid acidification of global oceans to _____ carbon emissions. | G8: Đã thuộc | H8: Dùng thay cho 'caused by human activities'
A9: 5 | B9: Environment & Climate Crisis | C9: exacerbate | D9: verb | /ɪɡˈzæs.ə.beɪt/ | E9: Làm trầm trọng thêm | F9: Uncontrolled industrial urbanization _____ topsoil degradation, rendering coastal deltas vulnerable to sea surges. | G9: Đã thuộc | H9: Trái nghĩa: mitigate, alleviate
A10: 6 | B10: Environment & Climate Crisis | C10: carbon sequestration | D10: noun phr | /ˌkɑː.bən ˌsiː.kwesˈtreɪ.ʃən/ | E10: Thu giữ & cô lập carbon | F10: Conserving virgin mangrove wetlands significantly enhances natural _____ and protects marine habitats. | G10: Đang học | H10: Động từ: sequester carbon
A11: 7 | B11: Technology & AI | C11: ubiquitous | D11: adj | /juːˈbɪk.wə.təs/ | E11: Phổ biến khắp mọi nơi | F11: Smart devices and automated algorithms have become _____ elements of contemporary urban civilization. | G11: Đã thuộc | H11: Đồng nghĩa: omnipresent, pervasive
A12: 8 | B12: Technology & AI | C12: disruptive | D12: adj | /dɪsˈrʌp.tɪv/ | E12: Mang tính đột phá triệt để | F12: Generative AI is a _____ technology that fundamentally transforms traditional workflows across creative industries. | G12: Đã thuộc | H12: Cụm: disruptive innovation / technology
A13: 9 | B13: Technology & AI | C13: obsolescence | D13: noun | /ˌɒb.səˈles.əns/ | E13: Sự trở nên lỗi thời | F13: Consumer electronics manufacturers are frequently criticized for practicing planned _____ to drive repeat purchases. | G13: Cần ôn lại | H13: Cụm: planned obsolescence (C2)
A14: 10 | B14: Society & Urbanization | C14: gentrification | D14: noun | /ˌdʒen.trɪ.fɪˈkeɪ.ʃən/ | E14: Chỉnh trang đô thị | F14: While urban _____ revitalizes dilapidated historic quarters, it frequently displaces working-class households. | G14: Đang học | H14: Động từ: gentrify a neighborhood
A15: 11 | B15: Society & Urbanization | C15: stratification | D15: noun | /ˌstræt.ɪ.fɪˈkeɪ.ʃən/ | E15: Sự phân tầng xã hội | F15: Widening gaps in capital accumulation deepen social _____ and reduce upward socioeconomic mobility. | G15: Đã thuộc | H15: Tính từ: stratified society
A16: 12 | B16: Society & Urbanization | C16: demographic dividend | D16: noun phr | /ˌdem.əˈɡræf.ɪk ˈdɪv.ɪ.dend/ | E16: Cơ cấu dân số vàng | F16: Developing economies must reform vocational education to effectively capitalize on their temporary _____. | G16: Đang học | H16: Khái niệm kinh tế dân số C2
... A34: 30 | B34: Psychology & Human Behavior | C34: cognitive dissonance | D34: noun phr | /ˌkɒɡ.nə.tɪv ˈdɪs.ə.nəns/ | E34: Bất hòa nhận thức | F34: Consumers who profess environmental values while buying disposable fast fashion experience acute psychological _____. | G34: Đang học | H34: Khái niệm tâm lý C2 kinh điển
