Workbook

Sheet Từ Vựng IELTS 4.5 - 6.0
A1: Topic | B1: Term | C1: PartOfSpeech | D1: Phonetic | E1: Definition | F1: CEFR | G1: Example | H1: Synonyms | I1: Antonyms | J1: Collocations | K1: Note | L1: Status
A2: Education & School Life | B2: academic | C2: adjective | D2: /ˌæk.əˈdem.ɪk/ | E2: Thuộc về học thuật, học tập tại trường viện | F2: B1 | G2: Students who possess strong academic performance often receive university scholarships. | H2: scholarly, educational, theoretical | I2: practical, non-academic, vocational | J2: academic performance, academic year, academic achievement | K2: Danh từ: academy (học viện), academician (viện sĩ). | L2: Đã thuộc
A3: Education & School Life | B3: curriculum | C3: noun | D3: /kəˈrɪk.jə.ləm/ | E3: Khung chương trình giảng dạy của nhà trường | F3: B2 | G3: The school curriculum includes basic mathematics, science, literature, and foreign languages. | H3: syllabus, study program, course of study | I3: extracurricular activity | J3: national curriculum, school curriculum, core curriculum | K3: Số nhiều: curricula /kəˈrɪk.jə.lə/ hoặc curriculums. | L3: Đang học
A4: Education & School Life | B4: extracurricular | C4: adjective | D4: /ˌek.strə.kəˈrɪk.jə.lər/ | E4: Ngoại khóa, diễn ra ngoài giờ học chính khóa | F4: B1 | G4: Participating in extracurricular activities like sports helps teenagers develop soft skills. | H4: after-school, non-academic, co-curricular | I4: curricular, academic, core | J4: extracurricular activities, extracurricular program, join clubs | K4: Extra- (bên ngoài) + curricular (thuộc chương trình học). | L4: Đã thuộc
A5: Education & School Life | B5: discipline | C5: noun/verb | D5: /ˈdɪs.ə.plɪn/ | E5: Tính kỷ luật / Rèn luyện kỷ luật; một ngành học | F5: B1 | G5: Self-discipline is essential for students who want to study independently at home. | H5: self-control, orderliness, regulation | I5: indiscipline, disorder, chaos | J5: maintain discipline, strict discipline, self-discipline | K5: Tính từ: disciplined. Trái nghĩa: undisciplined. | L5: Đã thuộc
A6: Education & School Life | B6: tuition fee | C6: noun phrase | D6: /tjuːˈɪʃ.ən fiː/ | E6: Học phí phải trả cho việc học tập tại trường | F6: B1 | G6: Rising university tuition fees make higher education unaffordable for poor families. | H6: tuition costs, school fees, course costs | I6: scholarship, grant, bursary | J6: pay tuition fees, affordable tuition fees, high tuition fees | K6: Thường dùng ở dạng số nhiều: tuition fees. | L6: Đã thuộc
A7: Education & School Life | B7: compulsory | C7: adjective | D7: /kəmˈpʌl.sər.i/ | E7: Bắt buộc theo quy định hoặc luật lệ | F7: B1 | G7: Primary education is compulsory for all children aged six to eleven in Vietnam. | H7: mandatory, obligatory, required, enforced | I7: optional, voluntary, elective | J7: compulsory education, compulsory subject, compulsory military service | K7: Động từ: compel (bắt buộc). Danh từ: compulsion. | L7: Đang học
A8: Education & School Life | B8: vocational | C8: adjective | D8: /vəʊˈkeɪ.ʃən.əl/ | E8: Thuộc về đào tạo nghề, hướng nghiệp thực hành | F8: B2 | G8: Vocational schools provide practical training in culinary arts, mechanics, and IT repair. | H8: career-oriented, technical, skill-based | I8: purely academic, theoretical | J8: vocational training, vocational school, vocational qualification | K8: Danh từ: vocation (thiên hướng nghề nghiệp phù hợp). | L8: Đang học
A9: Education & School Life | B9: scholarship | C9: noun | D9: /ˈskɒl.ə.ʃɪp/ | E9: Học bổng cấp cho học sinh giỏi hoặc khó khăn | F9: B1 | G9: She won a full scholarship to study environmental science in the United Kingdom. | H9: grant, financial aid, fellowship, bursary | I9: tuition debt, student loan | J9: win a scholarship, apply for a scholarship, full scholarship | K9: Người nhận học bổng / học giả: scholar. | L9: Đã thuộc
A10: Education & School Life | B10: evaluate | C10: verb | D10: /ɪˈvæl.ju.eɪt/ | E10: Đánh giá, chấm điểm chất lượng hoặc tiến độ học tập | F10: B2 | G10: Teachers evaluate student progress through weekly presentations and semester exams. | H10: assess, appraise, judge, rate, grade | I10: neglect, disregard, ignore | J10: evaluate progress, evaluate performance, carefully evaluate | K10: Danh từ: evaluation /ɪˌvæl.juˈeɪ.ʃən/ (sự đánh giá). | L10: Đang học
A11: Education & School Life | B11: qualification | C11: noun | D11: /ˌkwɒl.ɪ.fɪˈkeɪ.ʃən/ | E11: Bằng cấp, chứng chỉ chuyên môn hợp lệ | F11: B1 | G11: Having an internationally recognized English qualification improves job prospects. | H11: certificate, diploma, credential, degree | I11: incompetence, lack of skills | J11: gain a qualification, formal qualifications, academic qualification | K11: Động từ: qualify (qualify for a job). | L11: Đã thuộc
A12: Education & School Life | B12: memorize | C12: verb | D12: /ˈmem.ə.raɪz/ | E12: Ghi nhớ, học thuộc lòng thông tin hoặc từ vựng | F12: B1 | G12: Instead of trying to memorize whole paragraphs, learn key concepts and keywords. | H12: learn by heart, commit to memory, remember | I12: forget, overlook, unlearn | J12: memorize vocabulary, memorize formulas, memorize facts | K12: Danh từ: memory (trí nhớ / kỷ niệm). | L12: Đã thuộc
... A217: Science & Innovation | B217: sensor | C217: noun | D217: /ˈsen.sər/ | E217: Thiết bị cảm biến nhận biết nhiệt độ, chuyển động | F217: B1 | G217: Streetlights with motion sensors turn on only when pedestrians approach. | H217: detector, sensing device, transducer | I217: N/A | J217: motion sensor, temperature sensor, smart sensor | K217: Động từ: sense. | L217: Đã thuộc

Sheet Tổng Quan & Thống Kê
A1: TỔNG HỢP VÀ PHÂN TÍCH TỪ VỰNG IELTS BAND 4.5 - 6.0
A2: Hệ thống 216+ từ vựng nền tảng và phát triển học thuật (B1 - B2) phân bổ qua 12 chủ đề cốt lõi giúp bứt phá band điểm IELTS từ 4.5 lên 6.0 - 6.5+
B4: TỔNG SỐ TỪ VỰNG | D4: SỐ CHỦ ĐỀ CỐT LÕI | F4: TRÌNH ĐỘ B1 (NỀN TẢNG) | H4: TRÌNH ĐỘ B2 (BỨT PHÁ)
B5: =COUNTA('Từ Vựng IELTS 4.5 - 6.0'!B2:B217) | D5: 12 | F5: =COUNTIF('Từ Vựng IELTS 4.5 - 6.0'!F2:F217, "B1") + COUNTIF('Từ Vựng IELTS 4.5 - 6.0'!F2:F217, "A2") | H5: =COUNTIF('Từ Vựng IELTS 4.5 - 6.0'!F2:F217, "B2")
A8: BẢNG 1: PHÂN BỐ TỪ VỰNG THEO 12 CHỦ ĐỀ IELTS | F8: BẢNG 2: PHÂN BỐ THEO TRÌNH ĐỘ CEFR
A9: Mã & Tên Chủ Đề | B9: Số Từ Vựng | C9: Tỷ Lệ (%) | D9: Cấp Độ Mục Tiêu | F9: Cấp Độ CEFR | G9: Số Từ Vựng | H9: Tỷ Lệ (%)
A10: Education & School Life | B10: =COUNTIF('Từ Vựng IELTS 4.5 - 6.0'!$A$2:$A$217, A10) | C10: =B10/$B$22 | D10: Band 5.0 - 6.5 | F10: A2 | G10: =COUNTIF('Từ Vựng IELTS 4.5 - 6.0'!$F$2:$F$217, "A2") | H10: =G10/$G$13
A11: Environment & Climate | B11: =COUNTIF('Từ Vựng IELTS 4.5 - 6.0'!$A$2:$A$217, A11) | C11: =B11/$B$22 | D11: Band 5.0 - 6.5 | F11: B1 | G11: =COUNTIF('Từ Vựng IELTS 4.5 - 6.0'!$F$2:$F$217, "B1") | H11: =G11/$G$13
A12: Technology & Media | B12: =COUNTIF('Từ Vựng IELTS 4.5 - 6.0'!$A$2:$A$217, A12) | C12: =B12/$B$22 | D12: Band 5.0 - 6.5 | F12: B2 | G12: =COUNTIF('Từ Vựng IELTS 4.5 - 6.0'!$F$2:$F$217, "B2") | H12: =G12/$G$13
A13: Work & Business | B13: =COUNTIF('Từ Vựng IELTS 4.5 - 6.0'!$A$2:$A$217, A13) | C13: =B13/$B$22 | D13: Band 5.0 - 6.5 | F13: Tổng cộng | G13: =SUM(G10:G12) | H13: =SUM(H10:H12)
A14: Health & Fitness | B14: =COUNTIF('Từ Vựng IELTS 4.5 - 6.0'!$A$2:$A$217, A14) | C14: =B14/$B$22 | D14: Band 5.0 - 6.5
A15: Society & Family | B15: =COUNTIF('Từ Vựng IELTS 4.5 - 6.0'!$A$2:$A$217, A15) | C15: =B15/$B$22 | D15: Band 5.0 - 6.5
A16: Travel & Transport | B16: =COUNTIF('Từ Vựng IELTS 4.5 - 6.0'!$A$2:$A$217, A16) | C16: =B16/$B$22 | D16: Band 4.5 - 6.0
A17: Cities & Architecture | B17: =COUNTIF('Từ Vựng IELTS 4.5 - 6.0'!$A$2:$A$217, A17) | C17: =B17/$B$22 | D17: Band 5.0 - 6.5
A18: Arts & Culture | B18: =COUNTIF('Từ Vựng IELTS 4.5 - 6.0'!$A$2:$A$217, A18) | C18: =B18/$B$22 | D18: Band 5.0 - 6.5
A19: Crime & Social Issues | B19: =COUNTIF('Từ Vựng IELTS 4.5 - 6.0'!$A$2:$A$217, A19) | C19: =B19/$B$22 | D19: Band 5.0 - 6.5
A20: Shopping & Money | B20: =COUNTIF('Từ Vựng IELTS 4.5 - 6.0'!$A$2:$A$217, A20) | C20: =B20/$B$22 | D20: Band 4.5 - 6.0
A21: Science & Innovation | B21: =COUNTIF('Từ Vựng IELTS 4.5 - 6.0'!$A$2:$A$217, A21) | C21: =B21/$B$22 | D21: Band 5.0 - 6.5
A22: Tổng cộng | B22: =SUM(B10:B21) | C22: =SUM(C10:C21) | D22: 12 Chủ đề toàn diện
A42: LỘ TRÌNH VÀ CHIẾN LƯỢC BỨT PHÁ TỪ VỰNG IELTS TỪ BAND 4.5 LÊN 6.0 - 6.5+
A43: 1. Bước chuyển hóa từ vựng nền tảng (Từ B1 lên B2):
A44: Người học ở mức Band 4.5-5.0 thường phụ thuộc vào các từ vựng đơn giản (như good, bad, big, a lot of, help, solve). Để đạt Band 6.0-6.5+, bạn cần chuyển sang sử dụng các từ học thuật chuẩn xác (như beneficial, detrimental, substantial, facilitate, resolve).
A45: 2. Tuyệt đối học từ theo Cụm (Collocations Mastery):
A46: Không học từ vựng riêng lẻ. Hãy ghi nhớ cả cụm động từ và giới từ đi kèm (ví dụ: 'face redundancy', 'bridge the generation gap', 'traffic congestion', 'academic discipline', 'conserve energy'). Dùng đúng collocation giúp câu văn mượt mà và tự nhiên.
A47: 3. Nhận diện và làm chủ Họ từ (Word Families):
A48: Mỗi khi học một từ mới, hãy tra cứu đầy đủ danh từ, động từ, tính từ và trạng từ của từ đó (ví dụ: contaminate -> contamination -> contaminant; sustain -> sustainable -> sustainability). Tránh lỗi sai dạng từ (Word Form Error) thường gặp ở mức 5.0.
A49: 4. Rèn luyện kỹ năng Paraphrasing (Diễn đạt tương đương):
A50: Khai thác tối đa cột Synonyms (Từ đồng nghĩa) và Antonyms (Từ trái nghĩa) trong file để luyện tập viết lại đề bài (Introduction Paraphrasing) và triển khai luận điểm trong Writing Task 2 mà không bị lặp từ.
A51: 5. Áp dụng kỹ thuật Lặp lại ngắt quãng (Spaced Repetition):
A52: Sử dụng Tab 'Flashcard & Luyện Tập' để giải quyết 36 bài tập mẫu. Định kỳ chuyển trạng thái các từ hay quên thành 'Cần ôn lại' để ôn tập lại sau 1 ngày, 3 ngày, 7 ngày và 14 ngày cho đến khi thuộc lòng.

Sheet Flashcard & Luyện Tập
A1: BẢNG LUYỆN TẬP & ĐÁNH GIÁ MỨC ĐỘ GHI NHỚ TỪ VỰNG IELTS BAND 4.5 - 6.0
A2: Hướng dẫn: Tự điền từ vào chỗ trống trong các câu mẫu IELTS Writing/Speaking, sau đó đánh giá mức độ ghi nhớ ở cột 'Trạng Thái Ôn Tập' để lên kế hoạch ôn luyện định kỳ.
A4: STT | B4: Chủ Đề (Topic) | C4: Từ Cần Nhớ (Target Term) | D4: Loại Từ & Phiên Âm | E4: Định Nghĩa Tiếng Việt | F4: Câu Hỏi Luyện Tập (Điền từ vào chỗ trống) | G4: Trạng Thái Ôn Tập | H4: Ghi Chú Ôn Tập Cá Nhân
A5: 1 | B5: Education & School Life | C5: curriculum | D5: noun | /kəˈrɪk.jə.ləm/ | E5: Chương trình giảng dạy | F5: School authorities ought to incorporate practical financial literacy into the national secondary _____. | G5: Đã thuộc | H5: Số nhiều là curricula
A6: 2 | B6: Education & School Life | C6: compulsory | D6: adj | /kəmˈpʌl.sər.i/ | E6: Bắt buộc theo quy định | F6: In most modern societies, primary and lower-secondary schooling are made legally _____ for all children. | G6: Đã thuộc | H6: Trái nghĩa: optional / elective
A7: 3 | B7: Education & School Life | C7: vocational | D7: adj | /vəʊˈkeɪ.ʃən.əl/ | E7: Đào tạo nghề thực hành | F7: Attending _____ schools equips non-academic students with practical skills like carpentry and automotive repair. | G7: Đang học | H7: Danh từ: vocation
A8: 4 | B8: Environment & Climate | C8: deforestation | D8: noun | /diːˌfɒr.ɪˈsteɪ.ʃən/ | E8: Nạn chặt phá rừng | F8: Illegal commercial _____ in tropical regions destroys natural wildlife habitats and drives global warming. | G8: Đã thuộc | H8: Trái nghĩa: afforestation
A9: 5 | B9: Environment & Climate | C9: biodiversity | D9: noun | /ˌbaɪ.əʊ.daɪˈvɜː.sə.ti/ | E9: Đa dạng sinh học | F9: National parks are vital to preserve the rich _____ of endangered native plants and animal species. | G9: Đã thuộc | H9: Trọng âm 4: bi-o-di-VER-si-ty
A10: 6 | B10: Environment & Climate | C10: fossil fuel | D10: noun phr | /ˈfɒs.əl ˌfjuː.əl/ | E10: Nhiên liệu hóa thạch | F10: Phasing out our heavy reliance on _____ like coal and oil is crucial to meet international climate targets. | G10: Đang học | H10: Cụm: phase out fossil fuels
A11: 7 | B11: Technology & Media | C11: interactive | D11: adj | /ˌɪn.təˈræk.tɪv/ | E11: Có tính tương tác cao | F11: Smart classrooms use _____ touchscreens and educational software to engage students in dynamic learning. | G11: Đã thuộc | H11: Động từ: interact with
A12: 8 | B12: Technology & Media | C12: cybersecurity | D12: noun | /ˈsaɪ.bə.sɪˌkjʊə.rə.ti/ | E12: An ninh mạng số | F12: Multinational banking corporations invest millions annually to reinforce their digital _____ against hackers. | G12: Đang học | H12: Cyber- = không gian mạng
A13: 9 | B13: Technology & Media | C13: obsolete | D13: adj | /ˌɒb.səˈliːt/ | E13: Lỗi thời không dùng nữa | F13: The rapid creation of high-speed cloud storage has rendered physical floppy disks completely _____. | G13: Cần ôn lại | H13: Cụm: render sth obsolete
A14: 10 | B14: Work & Business | C14: applicant | D14: noun | /ˈæp.lɪ.kənt/ | E14: Người nộp đơn ứng tuyển | F14: More than two hundred qualified _____ submitted their resumes for the senior project manager vacancy. | G14: Đã thuộc | H14: Động từ: apply for
A15: 11 | B15: Work & Business | C15: entrepreneur | D15: noun | /ˌɒn.trə.prəˈnɜːr/ | E15: Doanh nhân khởi nghiệp | F15: Young tech _____ in Vietnam are developing creative mobile applications for international consumers. | G15: Đang học | H15: Trọng âm cuối: en-tre-pre-NEUR
A16: 12 | B16: Work & Business | C16: telecommuting | D16: noun | /ˌtel.ɪ.kəˈmjuː.tɪŋ/ | E16: Làm việc từ xa tại nhà | F16: Embracing _____ helps office employees save hours of daily commuting and improves work-life balance. | G16: Đã thuộc | H16: Đồng nghĩa: remote work / WFH
... A40: 36 | B40: Science & Innovation | C40: revolutionize | D40: verb | /ˌrev.əˈluː.ʃən.aɪz/ | E40: Cách mạng hóa sâu sắc | F40: The rapid creation of smartphones and mobile internet has completely _____ how humans communicate globally. | G40: Đã thuộc | H40: Danh từ: revolution
