Workbook

Sheet Từ Vựng IELTS 8.0 - 9.0
A1: Topic | B1: Term | C1: PartOfSpeech | D1: Phonetic | E1: Definition | F1: CEFR | G1: Example | H1: Synonyms | I1: Antonyms | J1: Collocations | K1: Note
A2: Epistemology & Philosophy | B2: hermeneutics | C2: noun | D2: /ˌhɜː.mɪˈnjuː.tɪks/ | E2: Khoa giải kinh, lý thuyết và phương pháp luận về sự diễn giải văn bản và ý nghĩa biểu tượng | F2: C2 | G2: Philosophical hermeneutics posits that human understanding is inherently contextual and historically conditioned. | H2: interpretive theory, textual exegesis, interpretive methodology | I2: literalism, uncritical reading | J2: philosophical hermeneutics, principles of hermeneutics, hermeneutic circle | K2: Tính từ: hermeneutic /ˌhɜː.mɪˈnjuː.tɪk/. Dùng phân tích chiều sâu diễn giải văn bản học thuật.
A3: Epistemology & Philosophy | B3: tautology | C3: noun | D3: /tɔːˈtɒl.ə.dʒi/ | E3: Phép lặp luận vô nghĩa, lỗi lập luận luẩn quẩn lặp lại cùng một ý bằng các từ khác nhau | F3: C2 | G3: Critics dismissed the minister's policy statement as a meaningless tautology devoid of substantive empirical evidence. | H3: circular reasoning, pleonasm, redundancy, reiteration | I3: substantive argument, empirical refutation | J3: logical tautology, redundant tautology, border on tautology | K3: Tính từ: tautological /ˌtɔː.təˈlɒdʒ.ɪ.kəl/. Dùng để phản biện sắc sảo lập luận ngụy biện.
A4: Epistemology & Philosophy | B4: heuristic | C4: adjective/noun | D4: /hjuˈrɪs.tɪk/ | E4: Mang tính phỏng đoán khám phá, phương pháp tìm tòi thực nghiệm giúp giải quyết vấn đề nhanh | F4: C1 | G4: Heuristic problem-solving techniques enable researchers to discover viable approximations when exact algorithms fail. | H4: exploratory, rule-of-thumb, trial-and-error, empirical | I4: algorithmic, deductive, rigid | J4: heuristic method, heuristic approach, cognitive heuristic, heuristic tool | K4: Số nhiều: heuristics (các phương pháp giải quyết vấn đề dựa trên kinh nghiệm).
A5: Epistemology & Philosophy | B5: dialectic | C5: noun | D5: /ˌdaɪ.əˈlek.tɪk/ | E5: Phép biện chứng, nghệ thuật tranh biện đối thoại giữa các ý kiến đối lập để tìm chân lý | F5: C2 | G5: Hegelian dialectic conceptualizes historical progress as an ongoing clash between thesis and antithesis culminating in synthesis. | H5: logical debate, philosophical argumentation, reasoned dialogue | I5: dogmatism, monologue | J5: Hegelian dialectic, Marxist dialectic, historical dialectic, dialectical method | K5: Tính từ: dialectical /ˌdaɪ.əˈlek.tɪ.kəl/ (dialectical reasoning = tư duy biện chứng).
A6: Epistemology & Philosophy | B6: epistemological | C6: adjective | D6: /ɪˌpɪs.tə.məˈlɒdʒ.ɪ.kəl/ | E6: Thuộc về nhận thức luận (nghiên cứu về bản chất, nguồn gốc và giới hạn của tri thức) | F6: C2 | G6: The advent of quantum mechanics precipitated a profound epistemological crisis in deterministic Newtonian physics. | H6: cognitive-philosophical, epistemological, gnoseological | I6: N/A | J6: epistemological framework, epistemological inquiry, epistemological crisis | K6: Danh từ: epistemology /ɪˌpɪs.təˈmɒl.ə.dʒi/. Thuật ngữ triết học học thuật đỉnh cao.
A7: Epistemology & Philosophy | B7: axiom | C7: noun | D7: /ˈæk.si.əm/ | E7: Tiên đề, nguyên lý tự hiển nhiên được chấp nhận là đúng mà không cần chứng minh | F7: C2 | G7: Classical economic theory rests upon the foundational axiom that individual consumers behave with perfect rationality. | H7: postulate, fundamental premise, self-evident truth, truism | I7: fallacy, hypothesis, unproven conjecture | J7: fundamental axiom, accepted axiom, basic axiom of science | K7: Tính từ: axiomatic /ˌæk.si.əˈmæt.ɪk/ (hiển nhiên, rõ ràng không cần bàn cãi).
A8: Epistemology & Philosophy | B8: teleological | C8: adjective | D8: /ˌtel.i.əˈlɒdʒ.ɪ.kəl/ | E8: Thuộc về mục đích luận (giải thích các hiện tượng tự nhiên dựa trên cứu cánh và mục đích cuối cùng) | F8: C2 | G8: Aristotelian philosophy adopts a teleological perspective, asserting that every entity in nature strives toward an ultimate telos. | H8: purpose-driven, finalistic, goal-directed | I8: mechanistic, accidental, causal | J8: teleological argument, teleological explanation, teleological view | K8: Danh từ: teleology /ˌtel.iˈɒl.ə.dʒi/. Gốc Hy Lạp 'telos' = mục đích cuối cùng.
A9: Epistemology & Philosophy | B9: dichotomy | C9: noun | D9: /daɪˈkɒt.ə.mi/ | E9: Sự phân đôi, thế lưỡng phân tương phản rạch ròi giữa hai thái cực hoàn toàn trái ngược | F9: C1 | G9: Scholars increasingly reject the rigid Cartesian dichotomy between the immaterial mind and the physical body. | H9: dualism, division, polarity, bifurcation, split | I9: unity, continuum, harmony, synthesis | J9: false dichotomy, sharp dichotomy, rigid dichotomy, bridge the dichotomy | K9: Cụm từ C2 rất hay gặp: 'fall into a false dichotomy' (mắc bẫy nhị phân giả tạo).
A10: Epistemology & Philosophy | B10: dogmatic | C10: adjective | D10: /dɒɡˈmæt.ɪk/ | E10: Giáo điều, võ đoán, khăng khăng bảo thủ áp đặt tín điều mà không cần bằng chứng | F10: C2 | G10: Rigorous scientific investigation demands empirical open-mindedness rather than uncritical adherence to dogmatic doctrines. | H10: doctrinaire, authoritarian, opinionated, inflexible, imperious | I10: open-minded, skeptical, pragmatic, flexible | J10: dogmatic assertion, dogmatic belief, dogmatic approach, highly dogmatic | K10: Danh từ: dogma (giáo điều) / dogmatism (chủ nghĩa giáo điều).
A11: Ecology & Anthropocene | B11: anthropocene | C11: noun | D11: /ˈæn.θrə.pəˌsiːn/ | E11: Kỷ Nhân sinh (kỷ nguyên địa chất hiện tại nơi hoạt động của con người là động lực biến đổi Trái Đất lớn nhất) | F11: C2 | G11: Geoscientists advocate formal recognition of the Anthropocene, citing indelible plastic strata and global radionuclide deposits. | H11: human epoch, post-Holocene era | I11: Holocene, pre-industrial era | J11: dawn of the Anthropocene, challenges of the Anthropocene, living in the Anthropocene | K11: Anthropo- (con người) + -cene (kỷ nguyên địa chất). Thuật ngữ học thuật danh giá.
A12: Ecology & Anthropocene | B12: biocentric | C12: adjective | D12: /ˌbaɪ.əʊˈsen.trɪk/ | E12: Lấy sinh giới làm trung tâm (quan điểm đạo đức sinh thái coi mọi sinh mệnh đều có giá trị tự thân bình đẳng) | F12: C2 | G12: Deep ecology advocates a biocentric worldview that categorically rejects the exploitative premises of human exceptionalism. | H12: ecocentric, life-centered, non-anthropocentric | I12: anthropocentric, human-centered | J12: biocentric ethics, biocentric philosophy, biocentric worldview | K12: Trái nghĩa trực tiếp với 'anthropocentric' (lấy con người làm trung tâm).
... A109: Behavioral Economics & Bias | B109: catharsis | C109: noun | D109: /kəˈθɑː.sɪs/ | E109: Sự giải tỏa thanh lọc cảm xúc (quá trình giải phóng các cảm xúc dồn nén thông qua nghệ thuật hoặc trải nghiệm kịch tính) | F109: C2 | G109: Classical Greek tragedy was engineered to evoke pity and fear, thereby inducing psychological catharsis in the audience. | H109: emotional release, purification, purgation, emotional cleansing | I109: emotional repression, bottling up, internal turmoil | J109: experience catharsis, emotional catharsis, provide catharsis | K109: Tính từ: cathartic /kəˈθɑː.tɪk/ (a cathartic experience = một trải nghiệm giải tỏa tâm lý).

Sheet Tổng Quan & Thống Kê
A1: TỔNG HỢP VÀ PHÂN TÍCH TỪ VỰNG HỌC THUẬT IELTS BAND 8.0 - 9.0
A2: Hệ thống 108+ thuật ngữ học thuật chuyên sâu C1-C2 (Expert Academic Lexicon & Nuances) phục vụ mục tiêu đạt điểm tuyệt đối tiêu chí Lexical Resource trong IELTS Writing Task 2 & Speaking Part 3
B4: TỔNG SỐ THUẬT NGỮ | D4: SỐ CHỦ ĐỀ HỌC THUẬT | F4: TRÌNH ĐỘ C1 (ADVANCED) | H4: TRÌNH ĐỘ C2 (MASTERY)
B5: =COUNTA('Từ Vựng IELTS 8.0 - 9.0'!B2:B109) | D5: 12 | F5: =COUNTIF('Từ Vựng IELTS 8.0 - 9.0'!F2:F109, "C1") | H5: =COUNTIF('Từ Vựng IELTS 8.0 - 9.0'!F2:F109, "C2")
A8: BẢNG 1: PHÂN BỐ THUẬT NGỮ THEO 12 CHỦ ĐỀ HỌC THUẬT ĐỈNH CAO | F8: BẢNG 2: PHÂN BỐ THEO TRÌNH ĐỘ CEFR
A9: Mã & Tên Chủ Đề | B9: Số Từ Vựng | C9: Tỷ Lệ (%) | D9: Mục Tiêu IELTS | F9: Cấp Độ CEFR | G9: Số Từ Vựng | H9: Tỷ Lệ (%)
A10: Epistemology & Philosophy | B10: =COUNTIF('Từ Vựng IELTS 8.0 - 9.0'!$A$2:$A$109, A10) | C10: =B10/$B$22 | D10: Band 8.5 - 9.0 | F10: C1 | G10: =COUNTIF('Từ Vựng IELTS 8.0 - 9.0'!$F$2:$F$109, "C1") | H10: =G10/$G$12
A11: Ecology & Anthropocene | B11: =COUNTIF('Từ Vựng IELTS 8.0 - 9.0'!$A$2:$A$109, A11) | C11: =B11/$B$22 | D11: Band 8.5 - 9.0 | F11: C2 | G11: =COUNTIF('Từ Vựng IELTS 8.0 - 9.0'!$F$2:$F$109, "C2") | H11: =G11/$G$12
A12: AI & Transhumanism | B12: =COUNTIF('Từ Vựng IELTS 8.0 - 9.0'!$A$2:$A$109, A12) | C12: =B12/$B$22 | D12: Band 8.5 - 9.0 | F12: Tổng cộng | G12: =SUM(G10:G11) | H12: =SUM(H10:H11)
A13: Sociology & Stratification | B13: =COUNTIF('Từ Vựng IELTS 8.0 - 9.0'!$A$2:$A$109, A13) | C13: =B13/$B$22 | D13: Band 8.5 - 9.0
A14: Macroeconomics & Finance | B14: =COUNTIF('Từ Vựng IELTS 8.0 - 9.0'!$A$2:$A$109, A14) | C14: =B14/$B$22 | D14: Band 8.5 - 9.0
A15: Bioethics & Epigenetics | B15: =COUNTIF('Từ Vựng IELTS 8.0 - 9.0'!$A$2:$A$109, A15) | C15: =B15/$B$22 | D15: Band 8.5 - 9.0
A16: Anthropology & Globalism | B16: =COUNTIF('Từ Vựng IELTS 8.0 - 9.0'!$A$2:$A$109, A16) | C16: =B16/$B$22 | D16: Band 8.5 - 9.0
A17: Jurisprudence & Criminology | B17: =COUNTIF('Từ Vựng IELTS 8.0 - 9.0'!$A$2:$A$109, A17) | C17: =B17/$B$22 | D17: Band 8.5 - 9.0
A18: Media & Semiotics | B18: =COUNTIF('Từ Vựng IELTS 8.0 - 9.0'!$A$2:$A$109, A18) | C18: =B18/$B$22 | D18: Band 8.5 - 9.0
A19: Governance & Realpolitik | B19: =COUNTIF('Từ Vựng IELTS 8.0 - 9.0'!$A$2:$A$109, A19) | C19: =B19/$B$22 | D19: Band 8.5 - 9.0
A20: Conservation & Bioethics | B20: =COUNTIF('Từ Vựng IELTS 8.0 - 9.0'!$A$2:$A$109, A20) | C20: =B20/$B$22 | D20: Band 8.0 - 9.0
A21: Behavioral Economics & Bias | B21: =COUNTIF('Từ Vựng IELTS 8.0 - 9.0'!$A$2:$A$109, A21) | C21: =B21/$B$22 | D21: Band 8.5 - 9.0
A22: Tổng cộng | B22: =SUM(B10:B21) | C22: =SUM(C10:C21) | D22: 12 Chủ đề chuyên gia
A42: CHIẾN LƯỢC ĐẠT ĐIỂM 9.0 TUYỆT ĐỐI TIÊU CHÍ LEXICAL RESOURCE (IELTS WRITING & SPEAKING)
A43: 1. Tiêu chuẩn vàng của Band 9.0 Lexical Resource (Natural and Sophisticated Control):
A44: Giám khảo Cambridge định nghĩa Band 9.0 là: 'Uses a wide range of vocabulary with very natural and sophisticated control of lexical features; rare minor errors occur only as slips'. Điều này đòi hỏi người học không chỉ biết từ khó mà phải sử dụng từ ngữ chuẩn xác tuyệt đối về phong cách học thuật (register), ngữ cảnh triết luận và không hề có dấu vết gượng ép.
A45: 2. Sử dụng Collocations học thuật C2 mang tính bản ngữ (Idiomatic Precision & Collocational Mastery):
A46: Điểm 9.0 đến từ sự kết hợp từ tinh tế (ví dụ: 'philosophical hermeneutics', 'reinforce biospheric homeostasis', 'trigger a trophic cascade', 'perpetuate systemic disenfranchisement', 'subtle cognitive dissonance'). Từ vựng phải hòa quyện tự nhiên vào luồng lập luận logic chặt chẽ.
A47: 3. Kiểm soát vi tế sắc thái biểu cảm và nguồn gốc thuật ngữ (Etymology & Conceptual Depth):
A48: Thí sinh Band 8.5-9.0 làm chủ sự khác biệt triết học sâu xa: 'hegemony' (sự thống trị bằng đồng thuận ngầm) vs 'coercion' (áp bức cưỡng chế); 'anthropocentric' (duy nhân loại) vs 'biocentric' (duy sinh giới); 'anomie' (vô chuẩn tắc đạo đức xã hội) vs 'chaos' (hỗn loạn thông thường).
A49: 4. Khả năng Paraphrasing học thuật biến hóa linh hoạt (Sophisticated Paraphrasing):
A50: Tránh hoàn toàn các cấu trúc diễn đạt khuôn sáo, thay vào đó vận dụng linh hoạt các thuật ngữ C1/C2 để tóm tắt các khái niệm phức tạp thành cụm từ cô đọng, sắc bén và giàu sức gợi (concise, high-density academic phrasing).
A51: 5. Kích hoạt và rèn luyện phản xạ ngôn ngữ chủ động (Active Lexical Deployment):
A52: Sử dụng Tab 'Flashcard & Luyện Tập' để giải quyết 30 câu hỏi mẫu Task 2/Speaking Part 3. Tự rèn luyện bằng cách đưa các thuật ngữ C2 này vào các bài luận chuyên sâu hàng tuần cho đến khi chúng trở thành phản xạ tư duy tự nhiên.

Sheet Flashcard & Luyện Tập
A1: BẢNG LUYỆN TẬP & ĐÁNH GIÁ MỨC ĐỘ GHI NHỚ TỪ VỰNG IELTS BAND 8.0 - 9.0
A2: Hướng dẫn: Tự điền từ vào chỗ trống trong các câu mẫu chuẩn văn phong IELTS Writing Task 2 & Speaking Part 3 (Band 8.5-9.0), sau đó đánh giá mức độ ghi nhớ ở cột 'Trạng Thái Ôn Tập'.
A4: STT | B4: Chủ Đề (Topic) | C4: Từ Cần Nhớ (Target Term) | D4: Loại Từ & Phiên Âm | E4: Định Nghĩa Tiếng Việt | F4: Câu Hỏi Luyện Tập (Điền từ vào chỗ trống) | G4: Trạng Thái Ôn Tập | H4: Ghi Chú Ôn Tập Cá Nhân
A5: 1 | B5: Epistemology & Philosophy | C5: hermeneutics | D5: noun | /ˌhɜː.mɪˈnjuː.tɪks/ | E5: Khoa giải kinh, lý thuyết diễn giải | F5: Philosophical _____ posits that human interpretation is fundamentally shaped by historical context and subjective prejudice. | G5: Đã thuộc | H5: Tính từ: hermeneutic circle
A6: 2 | B6: Epistemology & Philosophy | C6: tautology | D6: noun | /tɔːˈtɒl.ə.dʒi/ | E6: Lập luận luẩn quẩn vô nghĩa | F6: The politician's hollow assertion that 'free markets succeed because they work' is merely a redundant _____. | G6: Đang học | H6: Tính từ: tautological reasoning
A7: 3 | B7: Epistemology & Philosophy | C7: dichotomy | D7: noun | /daɪˈkɒt.ə.mi/ | E7: Thế lưỡng phân đối lập rạch ròi | F7: Modern cognitive scientists increasingly reject the Cartesian _____ that artificially separates the immaterial mind from the physical body. | G7: Đã thuộc | H7: Cụm: false dichotomy / rigid dichotomy
A8: 4 | B8: Ecology & Anthropocene | C8: anthropocene | D8: noun | /ˈæn.θrə.pəˌsiːn/ | E8: Kỷ Nhân sinh | F8: Stratigraphers argue that nuclear fallout and microplastics constitute indelible markers heralding the formal dawn of the _____. | G8: Đã thuộc | H8: Chủ đề địa chất - sinh thái C2
A9: 5 | B9: Ecology & Anthropocene | C9: biocentric | D9: adj | /ˌbaɪ.əʊˈsen.trɪk/ | E9: Lấy sinh giới làm trung tâm | F9: Deep ecology advocates a _____ ethics that attributes inherent moral worth to non-human organisms regardless of utility. | G9: Đang học | H9: Đối lập với anthropocentric
A10: 6 | B10: Ecology & Anthropocene | C10: trophic cascade | D10: noun phr | /ˈtrɒf.ɪk kæˈskeɪd/ | E10: Hiệu ứng thác dinh dưỡng | F10: The extirpation of top predators triggers a destabilizing _____ that radically alters downstream herbivore populations. | G10: Cần ôn lại | H10: Khái niệm sinh thái học C2
A11: 7 | B11: AI & Transhumanism | C11: transhumanism | D11: noun | /trænzˈhjuː.mən.ɪ.zəm/ | E11: Chủ nghĩa siêu nhân học | F11: Bioethicists intensely debate whether _____ represents evolutionary liberation or an existential threat to human nature. | G11: Đang học | H11: Tính từ: transhumanist movement
A12: 8 | B12: AI & Transhumanism | C12: technological singularity | D12: noun phr | /ˌtek.nəˈlɒdʒ.ɪ.kəl ˌsɪŋ.ɡjəˈlær.ə.ti/ | E12: Điểm kỳ dị công nghệ | F12: Futurists warn that approaching the _____ without alignment guarantees risks rendering human governance obsolete. | G12: Đã thuộc | H12: Khái niệm AI vượt trí tuệ người
A13: 9 | B13: AI & Transhumanism | C13: panoptic | D13: adj | /pænˈɒp.tɪk/ | E13: Giám sát toàn cảnh bao quát | F13: Ubiquitous data harvesting creates a _____ surveillance state where citizens' private choices are continuously monitored. | G13: Đang học | H13: Gốc từ Panopticon của Foucault
A14: 10 | B14: Sociology & Stratification | C14: meritocracy | D14: noun | /ˌmer.ɪˈtɒk.rə.si/ | E14: Chế độ trọng dụng nhân tài | F14: Critics argue that the illusion of pure _____ legitimizes structural class advantages under the guise of individual effort. | G14: Đã thuộc | H14: Tính từ: meritocratic society
A15: 11 | B15: Sociology & Stratification | C15: anomie | D15: noun | /ˈæn.ə.mi/ | E15: Tình trạng vô chuẩn tắc xã hội | F15: Durkheim observed that rapid economic disruption induces widespread social _____, eroding collective moral cohesion. | G15: Cần ôn lại | H15: Khái niệm xã hội học kinh điển
A16: 12 | B16: Sociology & Stratification | C16: demographic winter | D16: noun phr | /ˌdem.əˈɡræf.ɪk ˈwɪn.tər/ | E16: Mùa đông nhân khẩu học | F16: Sub-replacement fertility rates across developed nations threaten to usher in an economically devastating _____. | G16: Đã thuộc | H16: Ẩn dụ suy giảm sinh sản C2
... A34: 30 | B34: Behavioral Economics & Bias | C34: nudge theory | D34: noun phr | /ˈnʌdʒ ˌθɪə.ri/ | E34: Thuyết cú hích hành vi | F34: Public health agencies effectively harness _____ by redesigning choice architecture to subtly encourage nutritious dietary selections. | G34: Đã thuộc | H34: Nobel Kinh tế Richard Thaler
